[{"author": "peterinjapan", "author_flair_css_class": null, "author_flair_richtext": [], "author_flair_text": null, "author_flair_type": "text", "can_mod_post": false, "contest_mode": false, "created_utc": 1528168677, "domain": "self.stocks", "full_link": "https://www.reddit.com/r/stocks/comments/8onjot/your_top_three_etfs_xpost_retfs/", "gilded": 0, "id": "8onjot", "is_crosspostable": true, "is_original_content": false, "is_reddit_media_domain": false, "is_self": true, "is_video": false, "link_flair_richtext": [], "link_flair_text_color": "dark", "link_flair_type": "text", "locked": false, "media_only": false, "no_follow": true, "num_comments": 100, "num_crossposts": 0, "over_18": false, "parent_whitelist_status": "all_ads", "permalink": "/r/stocks/comments/8onjot/your_top_three_etfs_xpost_retfs/", "pinned": false, "pwls": 6, "retrieved_on": 1528168678, "rte_mode": "richtext", "score": 107, "selftext": "So what are your top three ETFs? Mine are\n\nMTUM: iShares momentum ETF, is built from stocks with upward momentum and rebalanced every 6 months I believe. I am having a hard time wondering why I shouldn't own a whole lot more of this.\n\nIVV: For all my attempts to be clever, I've made excellent returns by just holding the S&amp;P 500.\n\nDGRO: a dividend growth ETF that has performed well. It closely matches the S&amp;P 500 but with a significantly higher dividend, and is free of some problem stocks like REITs. \n\n\\(You can tell I have a big bias to iShares, because they are well organized and easy to understand, and I'm a Fidelity customer.\\)", "send_replies": true, "spoiler": false, "stickied": false, "subreddit": "stocks", "subreddit_id": "t5_2qjfk", "subreddit_subscribers": 241056, "subreddit_type": "public", "thumbnail": "self", "title": "Your top three ETFs? (x-post /r/etfs)", "url": "https://www.reddit.com/r/stocks/comments/8onjot/your_top_three_etfs_xpost_retfs/", "whitelist_status": "all_ads", "wls": 6}, {"author": "matrixdub", "author_flair_css_class": null, "author_flair_richtext": [], "author_flair_text": null, "author_flair_type": "text", "can_mod_post": false, "contest_mode": false, "created_utc": 1528124516, "domain": "self.stocks", "full_link": "https://www.reddit.com/r/stocks/comments/8ohxsc/nintendo_what_the_hell/", "gilded": 0, "id": "8ohxsc", "is_crosspostable": true, "is_original_content": false, "is_reddit_media_domain": false, "is_self": true, "is_video": false, "link_flair_richtext": [], "link_flair_text_color": "dark", "link_flair_type": "text", "locked": false, "media_only": false, "no_follow": true, "num_comments": 47, "num_crossposts": 0, "over_18": false, "parent_whitelist_status": "all_ads", "permalink": "/r/stocks/comments/8ohxsc/nintendo_what_the_hell/", "pinned": false, "pwls": 6, "retrieved_on": 1528124517, "rte_mode": "markdown", "score": 88, "selftext": "Why the sudden drops? Was it because of the horrible Mario aces demo which exposed just how terrible their online system is? I\u2019m thinking about selling but holding for E3", "send_replies": true, "spoiler": false, "stickied": false, "subreddit": "stocks", "subreddit_id": "t5_2qjfk", "subreddit_subscribers": 240920, "subreddit_type": "public", "thumbnail": "self", "title": "Nintendo.... what the hell?", "url": "https://www.reddit.com/r/stocks/comments/8ohxsc/nintendo_what_the_hell/", "whitelist_status": "all_ads", "wls": 6}, {"author": "SunnyW1479", "author_flair_css_class": null, "author_flair_richtext": [], "author_flair_text": null, "author_flair_type": "text", "can_mod_post": false, "contest_mode": false, "created_utc": 1528153901, "domain": "self.stocks", "full_link": "https://www.reddit.com/r/stocks/comments/8olvze/what_caused_chinese_stocks_to_pop_today/", "gilded": 0, "id": "8olvze", "is_crosspostable": true, "is_original_content": false, "is_reddit_media_domain": false, "is_self": true, "is_video": false, "link_flair_richtext": [], "link_flair_text_color": "dark", "link_flair_type": "text", "locked": false, "media_only": false, "no_follow": true, "num_comments": 14, "num_crossposts": 0, "over_18": false, "parent_whitelist_status": "all_ads", "permalink": "/r/stocks/comments/8olvze/what_caused_chinese_stocks_to_pop_today/", "pinned": false, "pwls": 6, "retrieved_on": 1528153902, "rte_mode": "markdown", "score": 17, "selftext": "JD, IQ, Bili, JD, BABA, SOGO, QD,all went up on large volume. Any guesses to what caused this?", "send_replies": false, "spoiler": false, "stickied": false, "subreddit": "stocks", "subreddit_id": "t5_2qjfk", "subreddit_subscribers": 241004, "subreddit_type": "public", "thumbnail": "self", "title": "What caused Chinese stocks to pop today?", "url": "https://www.reddit.com/r/stocks/comments/8olvze/what_caused_chinese_stocks_to_pop_today/", "whitelist_status": "all_ads", "wls": 6}, {"author": "tektonic_plates", "author_flair_css_class": null, "author_flair_richtext": [], "author_flair_text": null, "author_flair_type": "text", "can_mod_post": false, "contest_mode": false, "created_utc": 1528085508, "domain": "self.stocks", "full_link": "https://www.reddit.com/r/stocks/comments/8oegkv/mu_us_chipmaker_micron_one_of_three_companies/", "gilded": 0, "id": "8oegkv", "is_crosspostable": true, "is_original_content": false, "is_reddit_media_domain": false, "is_self": true, "is_video": false, "link_flair_richtext": [], "link_flair_text_color": "dark", "link_flair_type": "text", "locked": false, "media_only": false, "no_follow": true, "num_comments": 10, "num_crossposts": 0, "over_18": false, "parent_whitelist_status": "all_ads", "permalink": "/r/stocks/comments/8oegkv/mu_us_chipmaker_micron_one_of_three_companies/", "pinned": false, "pwls": 6, "retrieved_on": 1528085508, "rte_mode": "richtext", "score": 13, "selftext": "Just saw this news online:\n\n&gt;Three chipmaking companies\u2013one in the U.S. and two in South Korea\u2013are being investigated simultaneously by the Chinese government.  \n&gt;  \n&gt;Micron Technology, the largest American chipmaker; Samsung Electronics; and SK Hynix, the world\u2019s second\\-largest memory chipmaker, are being investigated by China\u2019s Anti\\-monopoly Bureau of State Administration for Market Regulation, Chinese news site Jiwei Net reported on June 1. Micron has since confirmed that the Chinese regulators visited its sales office on May 31 for information, according to [Bloomberg](https://www.bloomberg.com/news/articles/2018-06-01/micron-says-being-investigated-by-chinese-regulatory-agents).\n\nSource: [US Chipmaker Micron One of Three Companies Being Investigated By China](https://www.theepochtimes.com/us-chipmaker-micron-is-being-investigated-in-china_2547707.html), The Epoch Times ", "send_replies": true, "spoiler": false, "stickied": false, "subreddit": "stocks", "subreddit_id": "t5_2qjfk", "subreddit_subscribers": 240846, "subreddit_type": "public", "thumbnail": "self", "title": "$MU - US Chipmaker Micron One of Three Companies Being Investigated By China", "url": "https://www.reddit.com/r/stocks/comments/8oegkv/mu_us_chipmaker_micron_one_of_three_companies/", "whitelist_status": "all_ads", "wls": 6}, {"author": "northernsapsucker", "author_flair_css_class": null, "author_flair_richtext": [], "author_flair_text": null, "author_flair_type": "text", "can_mod_post": false, "contest_mode": false, "created_utc": 1528159626, "domain": "self.stocks", "full_link": "https://www.reddit.com/r/stocks/comments/8omjxl/why_do_investors_not_want_to_buy_ge_shares_right/", "gilded": 0, "id": "8omjxl", "is_crosspostable": true, "is_original_content": false, "is_reddit_media_domain": false, "is_self": true, "is_video": false, "link_flair_richtext": [], "link_flair_text_color": "dark", "link_flair_type": "text", "locked": false, "media_only": false, "no_follow": true, "num_comments": 13, "num_crossposts": 0, "over_18": false, "parent_whitelist_status": "all_ads", "permalink": "/r/stocks/comments/8omjxl/why_do_investors_not_want_to_buy_ge_shares_right/", "pinned": false, "pwls": 6, "retrieved_on": 1528159627, "rte_mode": "markdown", "score": 13, "selftext": "For context, I am an inexperienced investor and am looking for a greater understanding of the stock exchange on this subreddit.  \n\nTo elaborate on my original question, I have a few more specific questions:\n\n1. Does GE stock not have more potential than risk right now? From my understanding, now would be an ideal time to buy some stock in a massive company because it's so cheap.  In addition, there would be such a low risk if one were to buy a limited number of shares at the moment because one could only lose $14 per share at the most.  \n\n2. Is there any reason to believe the GE stock will not rise in value soon? \n\n3. Before buying, what kind of things should one look out for  that could cause such a fall in value?\n\nThanks to those of you who take your time to help me out.", "send_replies": true, "spoiler": false, "stickied": false, "subreddit": "stocks", "subreddit_id": "t5_2qjfk", "subreddit_subscribers": 241028, "subreddit_type": "public", "thumbnail": "self", "title": "Why do investors not want to buy GE shares right now?", "url": "https://www.reddit.com/r/stocks/comments/8omjxl/why_do_investors_not_want_to_buy_ge_shares_right/", "whitelist_status": "all_ads", "wls": 6}, {"author": "flatpack444", "author_flair_css_class": null, "author_flair_richtext": [], "author_flair_text": null, "author_flair_type": "text", "can_mod_post": false, "contest_mode": false, "created_utc": 1528144547, "domain": "self.stocks", "full_link": "https://www.reddit.com/r/stocks/comments/8okojh/how_do_you_do_your_dd/", "gilded": 0, "id": "8okojh", "is_crosspostable": true, "is_original_content": false, "is_reddit_media_domain": false, "is_self": true, "is_video": false, "link_flair_richtext": [], "link_flair_text_color": "dark", "link_flair_type": "text", "locked": false, "media_only": false, "no_follow": true, "num_comments": 13, "num_crossposts": 0, "over_18": false, "parent_whitelist_status": "all_ads", "permalink": "/r/stocks/comments/8okojh/how_do_you_do_your_dd/", "pinned": false, "pwls": 6, "retrieved_on": 1528144549, "rte_mode": "markdown", "score": 10, "selftext": "How do you screen for your next stock to invest in and what resources do you use to do your DD?  What websites or tools?", "send_replies": true, "spoiler": false, "stickied": false, "subreddit": "stocks", "subreddit_id": "t5_2qjfk", "subreddit_subscribers": 240974, "subreddit_type": "public", "thumbnail": "self", "title": "How do you do your DD?", "url": "https://www.reddit.com/r/stocks/comments/8okojh/how_do_you_do_your_dd/", "whitelist_status": "all_ads", "wls": 6}, {"author": "unrulyautopilot", "author_flair_css_class": null, "author_flair_richtext": [], "author_flair_text": null, "author_flair_type": "text", "can_mod_post": false, "contest_mode": false, "created_utc": 1528085787, "domain": "self.stocks", "full_link": "https://www.reddit.com/r/stocks/comments/8oehj2/blackberry_bb_resurrecting_a_forgotten_stock/", "gilded": 0, "id": "8oehj2", "is_crosspostable": true, "is_original_content": false, "is_reddit_media_domain": false, "is_self": true, "is_video": false, "link_flair_richtext": [], "link_flair_text_color": "dark", "link_flair_type": "text", "locked": false, "media_only": false, "no_follow": true, "num_comments": 17, "num_crossposts": 0, "over_18": false, "parent_whitelist_status": "all_ads", "permalink": "/r/stocks/comments/8oehj2/blackberry_bb_resurrecting_a_forgotten_stock/", "pinned": false, "pwls": 6, "retrieved_on": 1528085789, "rte_mode": "markdown", "score": 10, "selftext": "Blackberry has emerged over the past year or so as a major player in secure autonomous driving software systems. Partnerships are stacking up with Aptiv, Baidu, and Microsoft but it still seems to be flying under the radar. Is the baggage of the Blackberry brand holding back this stock? ", "send_replies": true, "spoiler": false, "stickied": false, "subreddit": "stocks", "subreddit_id": "t5_2qjfk", "subreddit_subscribers": 240846, "subreddit_type": "public", "thumbnail": "self", "title": "Blackberry ($BB), resurrecting a forgotten stock", "url": "https://www.reddit.com/r/stocks/comments/8oehj2/blackberry_bb_resurrecting_a_forgotten_stock/", "whitelist_status": "all_ads", "wls": 6}, {"author": "Walden_Walkabout", "author_flair_css_class": null, "author_flair_richtext": [], "author_flair_text": null, "author_flair_type": "text", "can_mod_post": false, "contest_mode": false, "created_utc": 1528124350, "domain": "self.stocks", "full_link": "https://www.reddit.com/r/stocks/comments/8ohwz3/fslr_down_6_on_the_day_seemingly_no_news/", "gilded": 0, "id": "8ohwz3", "is_crosspostable": true, "is_original_content": false, "is_reddit_media_domain": false, "is_self": true, "is_video": false, "link_flair_richtext": [], "link_flair_text_color": "dark", "link_flair_type": "text", "locked": false, "media_only": false, "no_follow": true, "num_comments": 7, "num_crossposts": 0, "over_18": false, "parent_whitelist_status": "all_ads", "permalink": "/r/stocks/comments/8ohwz3/fslr_down_6_on_the_day_seemingly_no_news/", "pinned": false, "pwls": 6, "retrieved_on": 1528124351, "rte_mode": "markdown", "score": 7, "selftext": "Title says it all. FSLR took a big hit, but I'm not seeing any real new or releases from them.", "send_replies": true, "spoiler": false, "stickied": false, "subreddit": "stocks", "subreddit_id": "t5_2qjfk", "subreddit_subscribers": 240917, "subreddit_type": "public", "thumbnail": "self", "title": "FSLR down 6% on the day, seemingly no news", "url": "https://www.reddit.com/r/stocks/comments/8ohwz3/fslr_down_6_on_the_day_seemingly_no_news/", "whitelist_status": "all_ads", "wls": 6}, {"author": "Molni", "author_flair_css_class": null, "author_flair_richtext": [], "author_flair_text": null, "author_flair_type": "text", "can_mod_post": false, "contest_mode": false, "created_utc": 1528135561, "domain": "self.stocks", "full_link": "https://www.reddit.com/r/stocks/comments/8ojfyn/iqiyi/", "gilded": 0, "id": "8ojfyn", "is_crosspostable": true, "is_original_content": false, "is_reddit_media_domain": false, "is_self": true, "is_video": false, "link_flair_richtext": [], "link_flair_text_color": "dark", "link_flair_type": "text", "locked": false, "media_only": false, "no_follow": true, "num_comments": 6, "num_crossposts": 0, "over_18": false, "parent_whitelist_status": "all_ads", "permalink": "/r/stocks/comments/8ojfyn/iqiyi/", "pinned": false, "pwls": 6, "retrieved_on": 1528135563, "rte_mode": "markdown", "score": 5, "selftext": "Get in or stay away? ", "send_replies": true, "spoiler": false, "stickied": false, "subreddit": "stocks", "subreddit_id": "t5_2qjfk", "subreddit_subscribers": 240944, "subreddit_type": "public", "thumbnail": "self", "title": "iQIYI", "url": "https://www.reddit.com/r/stocks/comments/8ojfyn/iqiyi/", "whitelist_status": "all_ads", "wls": 6}, {"author": "Mdizzle29", "author_flair_css_class": null, "author_flair_richtext": [], "author_flair_text": null, "author_flair_type": "text", "can_mod_post": false, "contest_mode": false, "created_utc": 1528131607, "domain": "self.stocks", "full_link": "https://www.reddit.com/r/stocks/comments/8oiwfw/question_on_tqqq_3x_leveraged_etf/", "gilded": 0, "id": "8oiwfw", "is_crosspostable": true, "is_original_content": false, "is_reddit_media_domain": false, "is_self": true, "is_video": false, "link_flair_richtext": [], "link_flair_text_color": "dark", "link_flair_type": "text", "locked": false, "media_only": false, "no_follow": true, "num_comments": 11, "num_crossposts": 0, "over_18": false, "parent_whitelist_status": "all_ads", "permalink": "/r/stocks/comments/8oiwfw/question_on_tqqq_3x_leveraged_etf/", "pinned": false, "pwls": 6, "retrieved_on": 1528131609, "rte_mode": "markdown", "score": 5, "selftext": "I\u2019m up 13.5% in about a month with this ETF. What is a good strategy? Take some off the table? Trailing stop loss? Curious about others who have won with this strategy.", "send_replies": true, "spoiler": false, "stickied": false, "subreddit": "stocks", "subreddit_id": "t5_2qjfk", "subreddit_subscribers": 240932, "subreddit_type": "public", "thumbnail": "self", "title": "Question on tQQQ (3x leveraged ETF)", "url": "https://www.reddit.com/r/stocks/comments/8oiwfw/question_on_tqqq_3x_leveraged_etf/", "whitelist_status": "all_ads", "wls": 6}, {"author": "Frosssty", "author_flair_css_class": null, "author_flair_richtext": [], "author_flair_text": null, "author_flair_type": "text", "can_mod_post": false, "contest_mode": false, "created_utc": 1528129247, "domain": "self.stocks", "full_link": "https://www.reddit.com/r/stocks/comments/8oil2j/down_50_on_csiq_with_the_incredibly_uncertain/", "gilded": 0, "id": "8oil2j", "is_crosspostable": true, "is_original_content": false, "is_reddit_media_domain": false, "is_self": true, "is_video": false, "link_flair_richtext": [], "link_flair_text_color": "dark", "link_flair_type": "text", "locked": false, "media_only": false, "no_follow": true, "num_comments": 13, "num_crossposts": 0, "over_18": false, "parent_whitelist_status": "all_ads", "permalink": "/r/stocks/comments/8oil2j/down_50_on_csiq_with_the_incredibly_uncertain/", "pinned": false, "pwls": 6, "retrieved_on": 1528129248, "rte_mode": "markdown", "score": 5, "selftext": "I've seen it recover +20% and then lose all of those gains within 3 days. My plan was to hold for the long term, but I cannot help feel like I'm losing money by not selling my losses and reinvesting into something more stable. Not a dividend payer, talks about company going private, Trump and Repubs circle-jerking over \"clean coal\", it seems like solar is going to be stagnant for the next 2-6 years. \n\nThoughts?", "send_replies": true, "spoiler": false, "stickied": false, "subreddit": "stocks", "subreddit_id": "t5_2qjfk", "subreddit_subscribers": 240930, "subreddit_type": "public", "thumbnail": "self", "title": "Down ~50% on $CSIQ. With the incredibly uncertain future of solar industry (short term), is it time to sell?", "url": "https://www.reddit.com/r/stocks/comments/8oil2j/down_50_on_csiq_with_the_incredibly_uncertain/", "whitelist_status": "all_ads", "wls": 6}, {"author": "whiskeynbeer2", "author_flair_css_class": null, "author_flair_richtext": [], "author_flair_text": null, "author_flair_type": "text", "can_mod_post": false, "contest_mode": false, "created_utc": 1528165449, "domain": "self.stocks", "full_link": "https://www.reddit.com/r/stocks/comments/8on7fj/v/", "gilded": 0, "id": "8on7fj", "is_crosspostable": true, "is_original_content": false, "is_reddit_media_domain": false, "is_self": true, "is_video": false, "link_flair_richtext": [], "link_flair_text_color": "dark", "link_flair_type": "text", "locked": false, "media_only": false, "no_follow": true, "num_comments": 5, "num_crossposts": 0, "over_18": false, "parent_whitelist_status": "all_ads", "permalink": "/r/stocks/comments/8on7fj/v/", "pinned": false, "pwls": 6, "retrieved_on": 1528165449, "rte_mode": "markdown", "score": 4, "selftext": "Any reason i shouldn\u2019t enter a leap to June 2019. ATM call. Can\u2019t find a reason outside the fact that v may be a little over price at the moment. ", "send_replies": true, "spoiler": false, "stickied": false, "subreddit": "stocks", "subreddit_id": "t5_2qjfk", "subreddit_subscribers": 241049, "subreddit_type": "public", "thumbnail": "self", "title": "V", "url": "https://www.reddit.com/r/stocks/comments/8on7fj/v/", "whitelist_status": "all_ads", "wls": 6}, {"author": "mpflug7", "author_flair_css_class": null, "author_flair_richtext": [], "author_flair_text": null, "author_flair_type": "text", "can_mod_post": false, "contest_mode": false, "created_utc": 1528109817, "domain": "self.stocks", "full_link": "https://www.reddit.com/r/stocks/comments/8ogcux/foxconn_ipo/", "gilded": 0, "id": "8ogcux", "is_crosspostable": true, "is_original_content": false, "is_reddit_media_domain": false, "is_self": true, "is_video": false, "link_flair_richtext": [], "link_flair_text_color": "dark", "link_flair_type": "text", "locked": false, "media_only": false, "no_follow": true, "num_comments": 3, "num_crossposts": 0, "over_18": false, "parent_whitelist_status": "all_ads", "permalink": "/r/stocks/comments/8ogcux/foxconn_ipo/", "pinned": false, "pwls": 6, "retrieved_on": 1528109818, "rte_mode": "markdown", "score": 3, "selftext": "So I was doing some research and saw that Foxconn was going public and that Alibaba, TenCent, and other Chinese companies have already invested. What do you guys think? When will it be available to trade in the US?", "send_replies": true, "spoiler": false, "stickied": false, "subreddit": "stocks", "subreddit_id": "t5_2qjfk", "subreddit_subscribers": 240891, "subreddit_type": "public", "thumbnail": "self", "title": "Foxconn IPO", "url": "https://www.reddit.com/r/stocks/comments/8ogcux/foxconn_ipo/", "whitelist_status": "all_ads", "wls": 6}, {"author": "suntoryBOSS_", "author_flair_css_class": null, "author_flair_richtext": [], "author_flair_text": null, "author_flair_type": "text", "can_mod_post": false, "contest_mode": false, "created_utc": 1528144401, "domain": "self.stocks", "full_link": "https://www.reddit.com/r/stocks/comments/8oknvh/time_to_short_sbux_howard_schultz_steps_down_as/", "gilded": 0, "id": "8oknvh", "is_crosspostable": true, "is_original_content": false, "is_reddit_media_domain": false, "is_self": true, "is_video": false, "link_flair_richtext": [], "link_flair_text_color": "dark", "link_flair_type": "text", "locked": false, "media_only": false, "no_follow": true, "num_comments": 6, "num_crossposts": 0, "over_18": false, "parent_whitelist_status": "all_ads", "permalink": "/r/stocks/comments/8oknvh/time_to_short_sbux_howard_schultz_steps_down_as/", "pinned": false, "pwls": 6, "retrieved_on": 1528144402, "rte_mode": "markdown", "score": 3, "selftext": "Just out - Howard Schultz is stepping down as CEO for Starbucks.\n\nAnyone playing this?\n\n[Article](https://www.cnbc.com/2018/06/04/howard-schultz-architect-of-modern-starbucks-to-step-down-as-executive-chair-and-from-the-board.html)", "send_replies": true, "spoiler": false, "stickied": false, "subreddit": "stocks", "subreddit_id": "t5_2qjfk", "subreddit_subscribers": 240974, "subreddit_type": "public", "thumbnail": "self", "title": "Time to short $SBUX? Howard Schultz steps down as CEO.", "url": "https://www.reddit.com/r/stocks/comments/8oknvh/time_to_short_sbux_howard_schultz_steps_down_as/", "whitelist_status": "all_ads", "wls": 6}, {"author": "McPick2000", "author_flair_css_class": null, "author_flair_richtext": [], "author_flair_text": null, "author_flair_type": "text", "can_mod_post": false, "contest_mode": false, "created_utc": 1528153217, "domain": "self.stocks", "full_link": "https://www.reddit.com/r/stocks/comments/8olsze/ua_up_10_in_5_days_and_is_trading_at_47x_earnings/", "gilded": 0, "id": "8olsze", "is_crosspostable": true, "is_original_content": false, "is_reddit_media_domain": false, "is_self": true, "is_video": false, "link_flair_richtext": [], "link_flair_text_color": "dark", "link_flair_type": "text", "locked": false, "media_only": false, "no_follow": true, "num_comments": 1, "num_crossposts": 0, "over_18": false, "parent_whitelist_status": "all_ads", "permalink": "/r/stocks/comments/8olsze/ua_up_10_in_5_days_and_is_trading_at_47x_earnings/", "pinned": false, "pwls": 6, "retrieved_on": 1528153218, "rte_mode": "markdown", "score": 2, "selftext": "", "send_replies": true, "spoiler": false, "stickied": false, "subreddit": "stocks", "subreddit_id": "t5_2qjfk", "subreddit_subscribers": 241003, "subreddit_type": "public", "thumbnail": "self", "title": "$UA up 10% in 5 days and is trading at 47x earnings. What am I missing here?", "url": "https://www.reddit.com/r/stocks/comments/8olsze/ua_up_10_in_5_days_and_is_trading_at_47x_earnings/", "whitelist_status": "all_ads", "wls": 6}, {"author": "Lyman-Zerga", "author_flair_css_class": null, "author_flair_richtext": [], "author_flair_text": null, "author_flair_type": "text", "can_mod_post": false, "contest_mode": false, "created_utc": 1528142043, "domain": "self.stocks", "full_link": "https://www.reddit.com/r/stocks/comments/8okc4s/atnm_oppenheimer_upgrade/", "gilded": 0, "id": "8okc4s", "is_crosspostable": true, "is_original_content": false, "is_reddit_media_domain": false, "is_self": true, "is_video": false, "link_flair_richtext": [], "link_flair_text_color": "dark", "link_flair_type": "text", "locked": false, "media_only": false, "no_follow": true, "num_comments": 0, "num_crossposts": 0, "over_18": false, "parent_whitelist_status": "all_ads", "permalink": "/r/stocks/comments/8okc4s/atnm_oppenheimer_upgrade/", "pinned": false, "pwls": 6, "retrieved_on": 1528142044, "rte_mode": "richtext", "score": 2, "selftext": " Shares of Actinium Pharmaceuticals Inc  \\(NYSEAMERICAN:ATNM\\) rose after Oppenheimer issued a US$5 price target on the stock ahead of what it expects to be several positive data readouts. \n\nThe analysts said they came away satisfied after a meeting with management where they discussed the firm\u2019s product pipeline.\n\nActinium\u2019s lead product candidate is Iomab\\-B that is in Phase 3  clinical studies for myeloablation and conditioning of the bone marrow  prior to a bone marrow transplants for older patients with relapsed or  refractory acute myeloid leukemia.\u00a0\n\n\u201cWith an increasingly clear line of sight to Iomab\\-B pivotal Phase 3  data \\(1H19, potential BLA filing 1H20\\) and mid\\-stage data in the growing  Actimab CD33 program, Actinium is on track to significantly re\\-rate in  2H18,\u201d wrote Oppenheimer analysts Hartaj Singh and Emma Nealon in a note  to clients.\n\nThe company is also developing Actimab\\-A, which is in Phase II clinical  trials for the treatment of patients over the age of 60 newly diagnosed  with a type of cancer of the blood and bone marrow.\n\n### Bullish view\n\n### The analysts assigned an Outperform rating with a $5 price target.\n\n\u201cActinium has three clinical assets: an alpha particle platform  technology and clinical trial support from the foremost bone marrow  transplant \\(BMT\\) centers in the US. Historical data and our physician  checks give us high conviction, and we conservatively assign a  risk\\-adjusted value of $2.60/share to Iomab\\-B and $2/ share to the other  programs,\u201d wrote the analysts.\u00a0\u00a0\n\n\u201cWe advise investors to carefully consider a misunderstood name.\u201d", "send_replies": true, "spoiler": false, "stickied": false, "subreddit": "stocks", "subreddit_id": "t5_2qjfk", "subreddit_subscribers": 240965, "subreddit_type": "public", "thumbnail": "self", "title": "$ATNM OPPENHEIMER UPGRADE", "url": "https://www.reddit.com/r/stocks/comments/8okc4s/atnm_oppenheimer_upgrade/", "whitelist_status": "all_ads", "wls": 6}, {"author": "luchins", "author_flair_css_class": null, "author_flair_richtext": [], "author_flair_text": null, "author_flair_type": "text", "can_mod_post": false, "contest_mode": false, "created_utc": 1528130052, "domain": "self.stocks", "full_link": "https://www.reddit.com/r/stocks/comments/8oioy2/tick_volume_graphic/", "gilded": 0, "id": "8oioy2", "is_crosspostable": true, "is_original_content": false, "is_reddit_media_domain": false, "is_self": true, "is_video": false, "link_flair_richtext": [], "link_flair_text_color": "dark", "link_flair_type": "text", "locked": false, "media_only": false, "no_follow": true, "num_comments": 0, "num_crossposts": 0, "over_18": false, "parent_whitelist_status": "all_ads", "permalink": "/r/stocks/comments/8oioy2/tick_volume_graphic/", "pinned": false, "pwls": 6, "retrieved_on": 1528130054, "rte_mode": "richtext", "score": 2, "selftext": "Hello can you help me out with the tick volume?   I can't really understand what is the difference between a candle graphic and a tick volume graphic   How can I spot ther price movement when I am using a tick\\-volume graphic?   I have red that it is the minimum price movement... well but isn' it the same of a ''normal'' candle graphic?  The candle chart also shows the minimum price movement at a given level...  I really can't understand the difference between the two  can you make a clear example please? So that I could understand in simple words?   I don't understand how the updates in the price movement can be helpful to take the decision to go long or short \\(along with other factors, obviously I wouldn't take only one indicator to decide if buy or sell\\)  For example if the price in that candle has been updated 101 times, well what does it mean?  Which kind of indicator can it be? A bearish candle with the price updated 101 times in the session, what could this ''suggest'' ? ", "send_replies": true, "spoiler": false, "stickied": false, "subreddit": "stocks", "subreddit_id": "t5_2qjfk", "subreddit_subscribers": 240931, "subreddit_type": "public", "thumbnail": "self", "title": "Tick volume graphic", "url": "https://www.reddit.com/r/stocks/comments/8oioy2/tick_volume_graphic/", "whitelist_status": "all_ads", "wls": 6}, {"author": "unrulyautopilot", "author_flair_css_class": null, "author_flair_richtext": [], "author_flair_text": null, "author_flair_type": "text", "can_mod_post": false, "contest_mode": false, "created_utc": 1528167835, "domain": "self.stocks", "full_link": "https://www.reddit.com/r/stocks/comments/8ongic/will_ferrari_race_be_affected_by_italian_debt/", "gilded": 0, "id": "8ongic", "is_crosspostable": true, "is_original_content": false, "is_reddit_media_domain": false, "is_self": true, "is_video": false, "link_flair_richtext": [], "link_flair_text_color": "dark", "link_flair_type": "text", "locked": false, "media_only": false, "no_follow": true, "num_comments": 9, "num_crossposts": 0, "over_18": false, "parent_whitelist_status": "all_ads", "permalink": "/r/stocks/comments/8ongic/will_ferrari_race_be_affected_by_italian_debt/", "pinned": false, "pwls": 6, "retrieved_on": 1528167835, "rte_mode": "markdown", "score": 2, "selftext": "With the rocky bond market in Italy, should we expect it to pull down $RACE or with many Italian corporates rated higher than government bonds, could this be a positive? ", "send_replies": true, "spoiler": false, "stickied": false, "subreddit": "stocks", "subreddit_id": "t5_2qjfk", "subreddit_subscribers": 241053, "subreddit_type": "public", "thumbnail": "self", "title": "Will Ferrari ($RACE) be affected by Italian debt markets?", "url": "https://www.reddit.com/r/stocks/comments/8ongic/will_ferrari_race_be_affected_by_italian_debt/", "whitelist_status": "all_ads", "wls": 6}, {"author": "timmssports", "author_flair_css_class": null, "author_flair_richtext": [], "author_flair_text": null, "author_flair_type": "text", "can_mod_post": false, "contest_mode": false, "created_utc": 1528120394, "domain": "self.stocks", "full_link": "https://www.reddit.com/r/stocks/comments/8ohf8a/selling_shares_beginner/", "gilded": 0, "id": "8ohf8a", "is_crosspostable": false, "is_original_content": false, "is_reddit_media_domain": false, "is_self": true, "is_video": false, "link_flair_richtext": [], "link_flair_text_color": "dark", "link_flair_type": "text", "locked": false, "media_only": false, "no_follow": true, "num_comments": 0, "num_crossposts": 0, "over_18": false, "parent_whitelist_status": "all_ads", "permalink": "/r/stocks/comments/8ohf8a/selling_shares_beginner/", "pinned": false, "pwls": 6, "retrieved_on": 1528120397, "rte_mode": "richtext", "score": 1, "selftext": "[removed]", "send_replies": true, "spoiler": false, "stickied": false, "subreddit": "stocks", "subreddit_id": "t5_2qjfk", "subreddit_subscribers": 240908, "subreddit_type": "public", "thumbnail": "self", "title": "Selling Shares (Beginner!)", "url": "https://www.reddit.com/r/stocks/comments/8ohf8a/selling_shares_beginner/", "whitelist_status": "all_ads", "wls": 6}, {"author": "Cubesss", "author_flair_css_class": null, "author_flair_richtext": [], "author_flair_text": null, "author_flair_type": "text", "can_mod_post": false, "contest_mode": false, "created_utc": 1528157009, "domain": "self.stocks", "full_link": "https://www.reddit.com/r/stocks/comments/8om94r/what_stock_indexs_to_buy/", "gilded": 0, "id": "8om94r", "is_crosspostable": false, "is_original_content": false, "is_reddit_media_domain": false, "is_self": true, "is_video": false, "link_flair_richtext": [], "link_flair_text_color": "dark", "link_flair_type": "text", "locked": false, "media_only": false, "no_follow": true, "num_comments": 0, "num_crossposts": 0, "over_18": false, "parent_whitelist_status": "all_ads", "permalink": "/r/stocks/comments/8om94r/what_stock_indexs_to_buy/", "pinned": false, "pwls": 6, "retrieved_on": 1528157010, "rte_mode": "markdown", "score": 1, "selftext": "[removed]", "send_replies": true, "spoiler": false, "stickied": false, "subreddit": "stocks", "subreddit_id": "t5_2qjfk", "subreddit_subscribers": 241015, "subreddit_type": "public", "thumbnail": "self", "title": "What stock index\u2019s to buy?", "url": "https://www.reddit.com/r/stocks/comments/8om94r/what_stock_indexs_to_buy/", "whitelist_status": "all_ads", "wls": 6}, {"author": "ABIO_Next_WINNER", "author_flair_css_class": null, "author_flair_richtext": [], "author_flair_text": null, "author_flair_type": "text", "can_mod_post": false, "contest_mode": false, "created_utc": 1528141678, "domain": "self.stocks", "full_link": "https://www.reddit.com/r/stocks/comments/8okaa6/ticker_abio_is_going_from_54_cents_to_200_in_a/", "gilded": 0, "id": "8okaa6", "is_crosspostable": false, "is_original_content": false, "is_reddit_media_domain": false, "is_self": true, "is_video": false, "link_flair_richtext": [], "link_flair_text_color": "dark", "link_flair_type": "text", "locked": false, "media_only": false, "no_follow": true, "num_comments": 0, "num_crossposts": 0, "over_18": false, "parent_whitelist_status": "all_ads", "permalink": "/r/stocks/comments/8okaa6/ticker_abio_is_going_from_54_cents_to_200_in_a/", "pinned": false, "pwls": 6, "retrieved_on": 1528141680, "rte_mode": "markdown", "score": 1, "selftext": "[removed]", "send_replies": true, "spoiler": false, "stickied": false, "subreddit": "stocks", "subreddit_id": "t5_2qjfk", "subreddit_subscribers": 240961, "subreddit_type": "public", "thumbnail": "self", "title": "TICKER $ABIO Is going from .54 cents to $2.00 in a few days MEETING WITH FDA=$$$ BUY BIOTECH COMPANY ABIO BIG MEDICAL DRUG !", "url": "https://www.reddit.com/r/stocks/comments/8okaa6/ticker_abio_is_going_from_54_cents_to_200_in_a/", "whitelist_status": "all_ads", "wls": 6}, {"author": "SamFish3r", "author_flair_css_class": null, "author_flair_richtext": [], "author_flair_text": null, "author_flair_type": "text", "can_mod_post": false, "contest_mode": false, "created_utc": 1528121112, "domain": "self.stocks", "full_link": "https://www.reddit.com/r/stocks/comments/8ohidh/looking_for_some_help_in_finding_stocks_outside/", "gilded": 0, "id": "8ohidh", "is_crosspostable": false, "is_original_content": false, "is_reddit_media_domain": false, "is_self": true, "is_video": false, "link_flair_background_color": "", "link_flair_css_class": "advicerequest", "link_flair_richtext": [{"e": "text", "t": "Advice Request"}], "link_flair_template_id": "75a227ec-65e6-11e5-96ee-12d48f46797b", "link_flair_text": "Advice Request", "link_flair_text_color": "dark", "link_flair_type": "richtext", "locked": false, "media_only": false, "no_follow": true, "num_comments": 1, "num_crossposts": 0, "over_18": false, "parent_whitelist_status": "all_ads", "permalink": "/r/stocks/comments/8ohidh/looking_for_some_help_in_finding_stocks_outside/", "pinned": false, "pwls": 6, "retrieved_on": 1528121114, "rte_mode": "markdown", "score": 1, "selftext": "[removed]", "send_replies": true, "spoiler": false, "stickied": false, "subreddit": "stocks", "subreddit_id": "t5_2qjfk", "subreddit_subscribers": 240910, "subreddit_type": "public", "thumbnail": "self", "title": "Looking for some help In finding stocks outside Tech sector that have a good growth potential, dividends would be a plus .", "url": "https://www.reddit.com/r/stocks/comments/8ohidh/looking_for_some_help_in_finding_stocks_outside/", "whitelist_status": "all_ads", "wls": 6}, {"author": "RockSolidTradin", "author_flair_css_class": null, "author_flair_richtext": [], "author_flair_text": null, "author_flair_type": "text", "can_mod_post": false, "contest_mode": false, "created_utc": 1528121715, "domain": "self.stocks", "full_link": "https://www.reddit.com/r/stocks/comments/8ohl3g/iq_volume_hit_57000000_and_counting/", "gilded": 0, "id": "8ohl3g", "is_crosspostable": false, "is_original_content": false, "is_reddit_media_domain": false, "is_self": true, "is_video": false, "link_flair_richtext": [], "link_flair_text_color": "dark", "link_flair_type": "text", "locked": false, "media_only": false, "no_follow": true, "num_comments": 0, "num_crossposts": 0, "over_18": false, "parent_whitelist_status": "all_ads", "permalink": "/r/stocks/comments/8ohl3g/iq_volume_hit_57000000_and_counting/", "pinned": false, "pwls": 6, "retrieved_on": 1528121717, "rte_mode": "richtext", "score": 1, "selftext": "[removed]", "send_replies": true, "spoiler": false, "stickied": false, "subreddit": "stocks", "subreddit_id": "t5_2qjfk", "subreddit_subscribers": 240910, "subreddit_type": "public", "thumbnail": "self", "title": "$IQ Volume hit 57,000,000 and counting !", "url": "https://www.reddit.com/r/stocks/comments/8ohl3g/iq_volume_hit_57000000_and_counting/", "whitelist_status": "all_ads", "wls": 6}, {"author": "rajatajmera99", "author_flair_css_class": null, "author_flair_richtext": [], "author_flair_text": null, "author_flair_type": "text", "can_mod_post": false, "contest_mode": false, "created_utc": 1528122237, "domain": "self.stocks", "full_link": "https://www.reddit.com/r/stocks/comments/8ohndy/investment_strategy_in_stock_market/", "gilded": 0, "id": "8ohndy", "is_crosspostable": true, "is_original_content": false, "is_reddit_media_domain": false, "is_self": true, "is_video": false, "link_flair_richtext": [], "link_flair_text_color": "dark", "link_flair_type": "text", "locked": false, "media_only": false, "no_follow": true, "num_comments": 0, "num_crossposts": 0, "over_18": false, "parent_whitelist_status": "all_ads", "permalink": "/r/stocks/comments/8ohndy/investment_strategy_in_stock_market/", "pinned": false, "pwls": 6, "retrieved_on": 1528122239, "rte_mode": "richtext", "score": 1, "selftext": "### [Investment Strategy In Stock Market](https://www.learnmarket.in/2018/05/profitable-investment-guide-in-stock.html) \n\n### How much money should be invested in Stocks?  \n\n### When to start investing in equities?   \n\n### The right sectors and stocks for investment \n\n### Selling or exit strategy \n\n### Systematic\u00a0selling and profit booking strategy ", "send_replies": true, "spoiler": false, "stickied": false, "subreddit": "stocks", "subreddit_id": "t5_2qjfk", "subreddit_subscribers": 240911, "subreddit_type": "public", "thumbnail": "self", "title": "Investment Strategy In Stock Market", "url": "https://www.reddit.com/r/stocks/comments/8ohndy/investment_strategy_in_stock_market/", "whitelist_status": "all_ads", "wls": 6}, {"author": "TheFreeman26", "author_flair_css_class": null, "author_flair_richtext": [], "author_flair_text": null, "author_flair_type": "text", "can_mod_post": false, "contest_mode": false, "created_utc": 1528102007, "domain": "self.stocks", "full_link": "https://www.reddit.com/r/stocks/comments/8ofrnb/im_a_new_investor_broker_site_suggestions/", "gilded": 0, "id": "8ofrnb", "is_crosspostable": false, "is_original_content": false, "is_reddit_media_domain": false, "is_self": true, "is_video": false, "link_flair_background_color": "", "link_flair_css_class": "advicerequest", "link_flair_richtext": [{"e": "text", "t": "Advice Request"}], "link_flair_template_id": "75a227ec-65e6-11e5-96ee-12d48f46797b", "link_flair_text": "Advice Request", "link_flair_text_color": "dark", "link_flair_type": "richtext", "locked": false, "media_only": false, "no_follow": true, "num_comments": 0, "num_crossposts": 0, "over_18": false, "parent_whitelist_status": "all_ads", "permalink": "/r/stocks/comments/8ofrnb/im_a_new_investor_broker_site_suggestions/", "pinned": false, "pwls": 6, "retrieved_on": 1528102009, "rte_mode": "markdown", "score": 1, "selftext": "[removed]", "send_replies": true, "spoiler": false, "stickied": false, "subreddit": "stocks", "subreddit_id": "t5_2qjfk", "subreddit_subscribers": 240880, "subreddit_type": "public", "thumbnail": "self", "title": "I'm a new investor, broker site suggestions?", "url": "https://www.reddit.com/r/stocks/comments/8ofrnb/im_a_new_investor_broker_site_suggestions/", "whitelist_status": "all_ads", "wls": 6}, {"author": "investinginvests", "author_flair_css_class": null, "author_flair_richtext": [], "author_flair_text": null, "author_flair_type": "text", "can_mod_post": false, "contest_mode": false, "created_utc": 1528118958, "domain": "self.stocks", "full_link": "https://www.reddit.com/r/stocks/comments/8oh9f7/lit_etf_hold_or_sell/", "gilded": 0, "id": "8oh9f7", "is_crosspostable": false, "is_original_content": false, "is_reddit_media_domain": false, "is_self": true, "is_video": false, "link_flair_richtext": [], "link_flair_text_color": "dark", "link_flair_type": "text", "locked": false, "media_only": false, "no_follow": true, "num_comments": 1, "num_crossposts": 0, "over_18": false, "parent_whitelist_status": "all_ads", "permalink": "/r/stocks/comments/8oh9f7/lit_etf_hold_or_sell/", "pinned": false, "pwls": 6, "retrieved_on": 1528118959, "rte_mode": "markdown", "score": 1, "selftext": "[removed]", "send_replies": true, "spoiler": false, "stickied": false, "subreddit": "stocks", "subreddit_id": "t5_2qjfk", "subreddit_subscribers": 240908, "subreddit_type": "public", "thumbnail": "self", "title": "LIT ETF - Hold or Sell?", "url": "https://www.reddit.com/r/stocks/comments/8oh9f7/lit_etf_hold_or_sell/", "whitelist_status": "all_ads", "wls": 6}, {"author": "whiskeynbeer2", "author_flair_css_class": null, "author_flair_richtext": [], "author_flair_text": null, "author_flair_type": "text", "can_mod_post": false, "contest_mode": false, "created_utc": 1528138663, "domain": "self.stocks", "full_link": "https://www.reddit.com/r/stocks/comments/8ojvc6/poor_mans_covered_calls_for_the_next_year/", "gilded": 0, "id": "8ojvc6", "is_crosspostable": true, "is_original_content": false, "is_reddit_media_domain": false, "is_self": true, "is_video": false, "link_flair_richtext": [], "link_flair_text_color": "dark", "link_flair_type": "text", "locked": false, "media_only": false, "no_follow": true, "num_comments": 3, "num_crossposts": 0, "over_18": false, "parent_whitelist_status": "all_ads", "permalink": "/r/stocks/comments/8ojvc6/poor_mans_covered_calls_for_the_next_year/", "pinned": false, "pwls": 6, "retrieved_on": 1528138664, "rte_mode": "markdown", "score": 1, "selftext": "What stocks look promising right now for everyone?\n\nBrk seems At a low but there\u2019s some buffet retirement rumors\n\nMsft aapl fb amzn and the Likes have all been on too much of a tear for me to get in on comfortably.\n\nChip stock etf? Maybe\n\nAny thoughts / advice is helpful thanks ", "send_replies": true, "spoiler": false, "stickied": false, "subreddit": "stocks", "subreddit_id": "t5_2qjfk", "subreddit_subscribers": 240949, "subreddit_type": "public", "thumbnail": "self", "title": "Poor mans covered calls for the next yeAr", "url": "https://www.reddit.com/r/stocks/comments/8ojvc6/poor_mans_covered_calls_for_the_next_year/", "whitelist_status": "all_ads", "wls": 6}, {"author": "TheFreeman26", "author_flair_css_class": null, "author_flair_richtext": [], "author_flair_text": null, "author_flair_type": "text", "can_mod_post": false, "contest_mode": false, "created_utc": 1528101302, "domain": "self.stocks", "full_link": "https://www.reddit.com/r/stocks/comments/8ofpwa/im_a_new_investor_recommended_site/", "gilded": 0, "id": "8ofpwa", "is_crosspostable": false, "is_original_content": false, "is_reddit_media_domain": false, "is_self": true, "is_video": false, "link_flair_background_color": "", "link_flair_css_class": "advicerequest", "link_flair_richtext": [{"e": "text", "t": "Advice Request"}], "link_flair_template_id": "75a227ec-65e6-11e5-96ee-12d48f46797b", "link_flair_text": "Advice Request", "link_flair_text_color": "dark", "link_flair_type": "richtext", "locked": false, "media_only": false, "no_follow": true, "num_comments": 0, "num_crossposts": 0, "over_18": false, "parent_whitelist_status": "all_ads", "permalink": "/r/stocks/comments/8ofpwa/im_a_new_investor_recommended_site/", "pinned": false, "pwls": 6, "retrieved_on": 1528101303, "rte_mode": "markdown", "score": 1, "selftext": "[removed]", "send_replies": true, "spoiler": false, "stickied": false, "subreddit": "stocks", "subreddit_id": "t5_2qjfk", "subreddit_subscribers": 240878, "subreddit_type": "public", "thumbnail": "self", "title": "I'm a new investor, recommended site?", "url": "https://www.reddit.com/r/stocks/comments/8ofpwa/im_a_new_investor_recommended_site/", "whitelist_status": "all_ads", "wls": 6}, {"author": "Nickyweg", "author_flair_css_class": null, "author_flair_richtext": [], "author_flair_text": null, "author_flair_type": "text", "can_mod_post": false, "contest_mode": false, "created_utc": 1528117940, "domain": "self.stocks", "full_link": "https://www.reddit.com/r/stocks/comments/8oh5c6/why_is_dis_so_cheap_right_now/", "gilded": 0, "id": "8oh5c6", "is_crosspostable": true, "is_original_content": false, "is_reddit_media_domain": false, "is_self": true, "is_video": false, "link_flair_richtext": [], "link_flair_text_color": "dark", "link_flair_type": "text", "locked": false, "media_only": false, "no_follow": true, "num_comments": 26, "num_crossposts": 0, "over_18": false, "parent_whitelist_status": "all_ads", "permalink": "/r/stocks/comments/8oh5c6/why_is_dis_so_cheap_right_now/", "pinned": false, "pwls": 6, "retrieved_on": 1528117942, "rte_mode": "markdown", "score": 1, "selftext": "It moved from the low 100s to $93. Any reason why? Is this a good time to get in or will or drop further? I assume the Fox hype will drive it up within the next few weeks. ", "send_replies": true, "spoiler": false, "stickied": false, "subreddit": "stocks", "subreddit_id": "t5_2qjfk", "subreddit_subscribers": 240907, "subreddit_type": "public", "thumbnail": "self", "title": "Why is DIS so cheap right now?", "url": "https://www.reddit.com/r/stocks/comments/8oh5c6/why_is_dis_so_cheap_right_now/", "whitelist_status": "all_ads", "wls": 6}, {"author": "Simplessence", "author_flair_css_class": null, "author_flair_richtext": [], "author_flair_text": null, "author_flair_type": "text", "can_mod_post": false, "contest_mode": false, "created_utc": 1528132037, "domain": "self.stocks", "full_link": "https://www.reddit.com/r/stocks/comments/8oiymk/why_doesnt_huge_short_float_ratio_decreases/", "gilded": 0, "id": "8oiymk", "is_crosspostable": true, "is_original_content": false, "is_reddit_media_domain": false, "is_self": true, "is_video": false, "link_flair_richtext": [], "link_flair_text_color": "dark", "link_flair_type": "text", "locked": false, "media_only": false, "no_follow": true, "num_comments": 6, "num_crossposts": 0, "over_18": false, "parent_whitelist_status": "all_ads", "permalink": "/r/stocks/comments/8oiymk/why_doesnt_huge_short_float_ratio_decreases/", "pinned": false, "pwls": 6, "retrieved_on": 1528132038, "rte_mode": "markdown", "score": 1, "selftext": "One of my stock has more than 30% of short float ratio. (i don't want to exposure here) and it has been soared up more than 20% from the bottom in a month. but there's no decrease of short float ratio at all though i thought it was short squeeze that pushed up the stock price. what's waiting ahead in general? short squeeze or stock price plunge?", "send_replies": true, "spoiler": false, "stickied": false, "subreddit": "stocks", "subreddit_id": "t5_2qjfk", "subreddit_subscribers": 240933, "subreddit_type": "public", "thumbnail": "self", "title": "Why doesn't huge Short Float Ratio decreases despite of rising stock price?", "url": "https://www.reddit.com/r/stocks/comments/8oiymk/why_doesnt_huge_short_float_ratio_decreases/", "whitelist_status": "all_ads", "wls": 6}, {"author": "luckystocknewb", "author_flair_css_class": null, "author_flair_richtext": [], "author_flair_text": null, "author_flair_type": "text", "can_mod_post": false, "contest_mode": false, "created_utc": 1528123164, "domain": "self.stocks", "full_link": "https://www.reddit.com/r/stocks/comments/8ohrm1/what_do_i_do_with_my_aal/", "gilded": 0, "id": "8ohrm1", "is_crosspostable": false, "is_original_content": false, "is_reddit_media_domain": false, "is_self": true, "is_video": false, "link_flair_richtext": [], "link_flair_text_color": "dark", "link_flair_type": "text", "locked": false, "media_only": false, "no_follow": true, "num_comments": 0, "num_crossposts": 0, "over_18": false, "parent_whitelist_status": "all_ads", "permalink": "/r/stocks/comments/8ohrm1/what_do_i_do_with_my_aal/", "pinned": false, "pwls": 6, "retrieved_on": 1528123165, "rte_mode": "markdown", "score": 1, "selftext": "[removed]", "send_replies": true, "spoiler": false, "stickied": false, "subreddit": "stocks", "subreddit_id": "t5_2qjfk", "subreddit_subscribers": 240914, "subreddit_type": "public", "thumbnail": "self", "title": "What do I do with my AAL?", "url": "https://www.reddit.com/r/stocks/comments/8ohrm1/what_do_i_do_with_my_aal/", "whitelist_status": "all_ads", "wls": 6}, {"author": "ArtisticProgrammer", "author_flair_css_class": null, "author_flair_richtext": [], "author_flair_text": null, "author_flair_type": "text", "can_mod_post": false, "contest_mode": false, "created_utc": 1528164247, "domain": "self.stocks", "full_link": "https://www.reddit.com/r/stocks/comments/8on2pv/what_will_the_market_do_if_trump_is_indicted/", "gilded": 0, "id": "8on2pv", "is_crosspostable": false, "is_original_content": false, "is_reddit_media_domain": false, "is_self": true, "is_video": false, "link_flair_richtext": [], "link_flair_text_color": "dark", "link_flair_type": "text", "locked": false, "media_only": false, "no_follow": true, "num_comments": 1, "num_crossposts": 0, "over_18": false, "parent_whitelist_status": "all_ads", "permalink": "/r/stocks/comments/8on2pv/what_will_the_market_do_if_trump_is_indicted/", "pinned": false, "pwls": 6, "retrieved_on": 1528164249, "rte_mode": "markdown", "score": 1, "selftext": "[removed]", "send_replies": true, "spoiler": false, "stickied": false, "subreddit": "stocks", "subreddit_id": "t5_2qjfk", "subreddit_subscribers": 241048, "subreddit_type": "public", "thumbnail": "self", "title": "What will the market do if Trump is indicted?", "url": "https://www.reddit.com/r/stocks/comments/8on2pv/what_will_the_market_do_if_trump_is_indicted/", "whitelist_status": "all_ads", "wls": 6}, {"author": "rouxbourbon", "author_flair_css_class": null, "author_flair_richtext": [], "author_flair_text": null, "author_flair_type": "text", "can_mod_post": false, "contest_mode": false, "created_utc": 1528162146, "domain": "self.stocks", "full_link": "https://www.reddit.com/r/stocks/comments/8omu7x/are_stop_losses_safe/", "gilded": 0, "id": "8omu7x", "is_crosspostable": true, "is_original_content": false, "is_reddit_media_domain": false, "is_self": true, "is_video": false, "link_flair_richtext": [], "link_flair_text_color": "dark", "link_flair_type": "text", "locked": false, "media_only": false, "no_follow": true, "num_comments": 4, "num_crossposts": 0, "over_18": false, "parent_whitelist_status": "all_ads", "permalink": "/r/stocks/comments/8omu7x/are_stop_losses_safe/", "pinned": false, "pwls": 6, "retrieved_on": 1528162147, "rte_mode": "richtext", "score": 1, "selftext": "So I am a new investor, and I hear the term risk quite often. I associate it to losing money on an investment. However; If I own 75 shares of something, and my average price paid per stock is $43. Can I not simply set a stop loss at $43.25 and eliminate the risk of loss? This may be a stupid question, but bear with me please...", "send_replies": true, "spoiler": false, "stickied": false, "subreddit": "stocks", "subreddit_id": "t5_2qjfk", "subreddit_subscribers": 241038, "subreddit_type": "public", "thumbnail": "self", "title": "Are Stop Losses Safe?", "url": "https://www.reddit.com/r/stocks/comments/8omu7x/are_stop_losses_safe/", "whitelist_status": "all_ads", "wls": 6}, {"author": "shyamshmkmr", "author_flair_css_class": null, "author_flair_richtext": [], "author_flair_text": null, "author_flair_type": "text", "can_mod_post": false, "contest_mode": false, "created_utc": 1528168692, "domain": "self.stocks", "full_link": "https://www.reddit.com/r/stocks/comments/8onjqr/microsoft_will_acquire_github_for_75_billion_in/", "gilded": 0, "id": "8onjqr", "is_crosspostable": false, "is_original_content": false, "is_reddit_media_domain": false, "is_self": true, "is_video": false, "link_flair_richtext": [], "link_flair_text_color": "dark", "link_flair_type": "text", "locked": false, "media_only": false, "no_follow": true, "num_comments": 1, "num_crossposts": 0, "over_18": false, "parent_whitelist_status": "all_ads", "permalink": "/r/stocks/comments/8onjqr/microsoft_will_acquire_github_for_75_billion_in/", "pinned": false, "pwls": 6, "retrieved_on": 1528168693, "rte_mode": "markdown", "score": 1, "selftext": "[removed]", "send_replies": true, "spoiler": false, "stickied": false, "subreddit": "stocks", "subreddit_id": "t5_2qjfk", "subreddit_subscribers": 241056, "subreddit_type": "public", "thumbnail": "self", "title": "Microsoft will acquire GitHub for $7.5 billion in Microsoft stock.Can anyone explain how this work.", "url": "https://www.reddit.com/r/stocks/comments/8onjqr/microsoft_will_acquire_github_for_75_billion_in/", "whitelist_status": "all_ads", "wls": 6}, {"author": "Vinesh_red", "author_flair_css_class": null, "author_flair_richtext": [], "author_flair_text": null, "author_flair_type": "text", "can_mod_post": false, "contest_mode": false, "created_utc": 1528168837, "domain": "self.stocks", "full_link": "https://www.reddit.com/r/stocks/comments/8onk8e/robinhoodpassword_resetlost_all_portfolio_pls/", "gilded": 0, "id": "8onk8e", "is_crosspostable": false, "is_original_content": false, "is_reddit_media_domain": false, "is_self": true, "is_video": false, "link_flair_richtext": [], "link_flair_text_color": "dark", "link_flair_type": "text", "locked": false, "media_only": false, "no_follow": true, "num_comments": 0, "num_crossposts": 0, "over_18": false, "parent_whitelist_status": "all_ads", "permalink": "/r/stocks/comments/8onk8e/robinhoodpassword_resetlost_all_portfolio_pls/", "pinned": false, "pwls": 6, "retrieved_on": 1528168838, "rte_mode": "markdown", "score": 1, "selftext": "[removed]", "send_replies": true, "spoiler": false, "stickied": false, "subreddit": "stocks", "subreddit_id": "t5_2qjfk", "subreddit_subscribers": 241057, "subreddit_type": "public", "thumbnail": "self", "title": "Robinhood&lt;password reset&lt;lost all portfolio Pls Advice", "url": "https://www.reddit.com/r/stocks/comments/8onk8e/robinhoodpassword_resetlost_all_portfolio_pls/", "whitelist_status": "all_ads", "wls": 6}, {"author": "shamgar_bn", "author_flair_css_class": null, "author_flair_richtext": [], "author_flair_text": null, "author_flair_type": "text", "can_mod_post": false, "contest_mode": false, "created_utc": 1528136850, "domain": "self.stocks", "full_link": "https://www.reddit.com/r/stocks/comments/8ojmgz/lxft_analysis_request/", "gilded": 0, "id": "8ojmgz", "is_crosspostable": true, "is_original_content": false, "is_reddit_media_domain": false, "is_self": true, "is_video": false, "link_flair_richtext": [], "link_flair_text_color": "dark", "link_flair_type": "text", "locked": false, "media_only": false, "no_follow": true, "num_comments": 1, "num_crossposts": 0, "over_18": false, "parent_whitelist_status": "all_ads", "permalink": "/r/stocks/comments/8ojmgz/lxft_analysis_request/", "pinned": false, "pwls": 6, "retrieved_on": 1528136852, "rte_mode": "markdown", "score": 1, "selftext": "According to my analysis, LXFT is at a good buying point, but my valuation seems too good to be true, which is causing me to doubt my numbers. Can anyone else provide their thoughts or analysis on the current and future value of LXFT?\n\nThanks!", "send_replies": true, "spoiler": false, "stickied": false, "subreddit": "stocks", "subreddit_id": "t5_2qjfk", "subreddit_subscribers": 240946, "subreddit_type": "public", "thumbnail": "self", "title": "LXFT analysis request", "url": "https://www.reddit.com/r/stocks/comments/8ojmgz/lxft_analysis_request/", "whitelist_status": "all_ads", "wls": 6}, {"author": "peacetrain4kis", "author_flair_css_class": null, "author_flair_richtext": [], "author_flair_text": null, "author_flair_type": "text", "can_mod_post": false, "contest_mode": false, "created_utc": 1528142044, "domain": "self.stocks", "full_link": "https://www.reddit.com/r/stocks/comments/8okc52/best_penny_stocks_to_buy/", "gilded": 0, "id": "8okc52", "is_crosspostable": true, "is_original_content": false, "is_reddit_media_domain": false, "is_self": true, "is_video": false, "link_flair_richtext": [], "link_flair_text_color": "dark", "link_flair_type": "text", "locked": false, "media_only": false, "no_follow": true, "num_comments": 0, "num_crossposts": 0, "over_18": false, "parent_whitelist_status": "all_ads", "permalink": "/r/stocks/comments/8okc52/best_penny_stocks_to_buy/", "pinned": false, "pwls": 6, "retrieved_on": 1528142045, "rte_mode": "richtext", "score": 1, "selftext": "1. Organovo Holdings Inc\n\nThis is a new company that is working with ground breaking medical technology that has a bright future.\n\n2.   SUNWORKS INC\n\nthis is a flaming company that is going to make a come back and get big.", "send_replies": true, "spoiler": false, "stickied": false, "subreddit": "stocks", "subreddit_id": "t5_2qjfk", "subreddit_subscribers": 240965, "subreddit_type": "public", "thumbnail": "self", "title": "Best penny stocks to buy", "url": "https://www.reddit.com/r/stocks/comments/8okc52/best_penny_stocks_to_buy/", "whitelist_status": "all_ads", "wls": 6}, {"author": "f1shb0nez", "author_flair_css_class": null, "author_flair_richtext": [], "author_flair_text": null, "author_flair_type": "text", "can_mod_post": false, "contest_mode": false, "created_utc": 1528093117, "domain": "self.stocks", "full_link": "https://www.reddit.com/r/stocks/comments/8of4b7/microsoft_msft_has_reportedly_acquired_github/", "gilded": 0, "id": "8of4b7", "is_crosspostable": false, "is_original_content": false, "is_reddit_media_domain": false, "is_self": true, "is_video": false, "link_flair_richtext": [], "link_flair_text_color": "dark", "link_flair_type": "text", "locked": false, "media_only": false, "no_follow": true, "num_comments": 1, "num_crossposts": 0, "over_18": false, "parent_whitelist_status": "all_ads", "permalink": "/r/stocks/comments/8of4b7/microsoft_msft_has_reportedly_acquired_github/", "pinned": false, "post_hint": "self", "preview": {"enabled": false, "images": [{"id": "bxrWZf0TP_MoZ2v4ZIXJyA5Qxz6KEBT2k7u9_vE0rJ4", "resolutions": [{"height": 56, "url": "https://i.redditmedia.com/0v2oJJvx1FuPf132xBruda0gqo4oNHeKjH4CfGW6WM4.jpg?fit=crop&amp;crop=faces%2Centropy&amp;arh=2&amp;w=108&amp;s=94a7bf4031963d08f09c4cbaca461ec5", "width": 108}, {"height": 113, "url": "https://i.redditmedia.com/0v2oJJvx1FuPf132xBruda0gqo4oNHeKjH4CfGW6WM4.jpg?fit=crop&amp;crop=faces%2Centropy&amp;arh=2&amp;w=216&amp;s=78c2784842e08076d7a4c659f76c7c9b", "width": 216}, {"height": 167, "url": "https://i.redditmedia.com/0v2oJJvx1FuPf132xBruda0gqo4oNHeKjH4CfGW6WM4.jpg?fit=crop&amp;crop=faces%2Centropy&amp;arh=2&amp;w=320&amp;s=355d624b559c3346fad12a8268567e62", "width": 320}, {"height": 334, "url": "https://i.redditmedia.com/0v2oJJvx1FuPf132xBruda0gqo4oNHeKjH4CfGW6WM4.jpg?fit=crop&amp;crop=faces%2Centropy&amp;arh=2&amp;w=640&amp;s=e0eb4559a27576401069c321eda631b1", "width": 640}, {"height": 502, "url": "https://i.redditmedia.com/0v2oJJvx1FuPf132xBruda0gqo4oNHeKjH4CfGW6WM4.jpg?fit=crop&amp;crop=faces%2Centropy&amp;arh=2&amp;w=960&amp;s=637e4dc0a3b3aaabfa561b33856be7b8", "width": 960}, {"height": 565, "url": "https://i.redditmedia.com/0v2oJJvx1FuPf132xBruda0gqo4oNHeKjH4CfGW6WM4.jpg?fit=crop&amp;crop=faces%2Centropy&amp;arh=2&amp;w=1080&amp;s=3f3311bba2937310bc24741a1a78f64e", "width": 1080}], "source": {"height": 628, "url": "https://i.redditmedia.com/0v2oJJvx1FuPf132xBruda0gqo4oNHeKjH4CfGW6WM4.jpg?s=399a4f64b63416944eba7d72ec8145ce", "width": 1200}, "variants": {}}]}, "pwls": 6, "retrieved_on": 1528093118, "rte_mode": "markdown", "score": 1, "selftext": "[removed]", "send_replies": true, "spoiler": false, "stickied": false, "subreddit": "stocks", "subreddit_id": "t5_2qjfk", "subreddit_subscribers": 240873, "subreddit_type": "public", "thumbnail": "self", "title": "Microsoft (MSFT) has reportedly acquired GitHub", "url": "https://www.reddit.com/r/stocks/comments/8of4b7/microsoft_msft_has_reportedly_acquired_github/", "whitelist_status": "all_ads", "wls": 6}, {"author": "1ECz", "author_flair_css_class": null, "author_flair_richtext": [], "author_flair_text": null, "author_flair_type": "text", "can_mod_post": false, "contest_mode": false, "created_utc": 1528088151, "domain": "self.stocks", "full_link": "https://www.reddit.com/r/stocks/comments/8oepdm/trades_historical_intraday_data/", "gilded": 0, "id": "8oepdm", "is_crosspostable": true, "is_original_content": false, "is_reddit_media_domain": false, "is_self": true, "is_video": false, "link_flair_richtext": [], "link_flair_text_color": "dark", "link_flair_type": "text", "locked": false, "media_only": false, "no_follow": true, "num_comments": 2, "num_crossposts": 0, "over_18": false, "parent_whitelist_status": "all_ads", "permalink": "/r/stocks/comments/8oepdm/trades_historical_intraday_data/", "pinned": false, "pwls": 6, "retrieved_on": 1528088153, "rte_mode": "markdown", "score": 0, "selftext": "Hello,\n\nAfter googling for 5hr, I could not find the free historical data for intraday trades. \n\nduration: 10yr\nexchange: Nasdaq\nprecision: 1 min\n\nDo you have any recommendation other than paying for it ?", "send_replies": true, "spoiler": false, "stickied": false, "subreddit": "stocks", "subreddit_id": "t5_2qjfk", "subreddit_subscribers": 240856, "subreddit_type": "public", "thumbnail": "self", "title": "Trades historical intraday data.", "url": "https://www.reddit.com/r/stocks/comments/8oepdm/trades_historical_intraday_data/", "whitelist_status": "all_ads", "wls": 6}, {"author": "McBluffin82", "author_flair_css_class": null, "author_flair_richtext": [], "author_flair_text": null, "author_flair_type": "text", "can_mod_post": false, "contest_mode": false, "created_utc": 1528159392, "domain": "self.stocks", "full_link": "https://www.reddit.com/r/stocks/comments/8omizw/what_are_you_opinions_on_txmd_postapproval/", "gilded": 0, "id": "8omizw", "is_crosspostable": false, "is_original_content": false, "is_reddit_media_domain": false, "is_self": true, "is_video": false, "link_flair_richtext": [], "link_flair_text_color": "dark", "link_flair_type": "text", "locked": false, "media_only": false, "no_follow": true, "num_comments": 2, "num_crossposts": 0, "over_18": false, "parent_whitelist_status": "all_ads", "permalink": "/r/stocks/comments/8omizw/what_are_you_opinions_on_txmd_postapproval/", "pinned": false, "pwls": 6, "retrieved_on": 1528159393, "rte_mode": "markdown", "score": 0, "selftext": "[removed]", "send_replies": true, "spoiler": false, "stickied": false, "subreddit": "stocks", "subreddit_id": "t5_2qjfk", "subreddit_subscribers": 241025, "subreddit_type": "public", "thumbnail": "self", "title": "What are you opinions on TXMD post-approval?", "url": "https://www.reddit.com/r/stocks/comments/8omizw/what_are_you_opinions_on_txmd_postapproval/", "whitelist_status": "all_ads", "wls": 6}, {"author": "Cubesss", "author_flair_css_class": null, "author_flair_richtext": [], "author_flair_text": null, "author_flair_type": "text", "can_mod_post": false, "contest_mode": false, "created_utc": 1528160022, "domain": "self.stocks", "full_link": "https://www.reddit.com/r/stocks/comments/8omlmh/which_stock_indexes/", "gilded": 0, "id": "8omlmh", "is_crosspostable": true, "is_original_content": false, "is_reddit_media_domain": false, "is_self": true, "is_video": false, "link_flair_richtext": [], "link_flair_text_color": "dark", "link_flair_type": "text", "locked": false, "media_only": false, "no_follow": true, "num_comments": 6, "num_crossposts": 0, "over_18": false, "parent_whitelist_status": "all_ads", "permalink": "/r/stocks/comments/8omlmh/which_stock_indexes/", "pinned": false, "pwls": 6, "retrieved_on": 1528160023, "rte_mode": "markdown", "score": 0, "selftext": "I have a background in finance and accounting looking to invest some extra money in some high growth indexes. Any recommendations? ", "send_replies": true, "spoiler": false, "stickied": false, "subreddit": "stocks", "subreddit_id": "t5_2qjfk", "subreddit_subscribers": 241029, "subreddit_type": "public", "thumbnail": "self", "title": "Which Stock Indexes?", "url": "https://www.reddit.com/r/stocks/comments/8omlmh/which_stock_indexes/", "whitelist_status": "all_ads", "wls": 6}, {"author": "Beautifile", "author_flair_css_class": null, "author_flair_richtext": [], "author_flair_text": null, "author_flair_type": "text", "can_mod_post": false, "contest_mode": false, "created_utc": 1528089353, "domain": "self.stocks", "full_link": "https://www.reddit.com/r/stocks/comments/8oet2e/advice_on_buying_a_stock_with_very_little_info/", "gilded": 0, "id": "8oet2e", "is_crosspostable": true, "is_original_content": false, "is_reddit_media_domain": false, "is_self": true, "is_video": false, "link_flair_richtext": [], "link_flair_text_color": "dark", "link_flair_type": "text", "locked": false, "media_only": false, "no_follow": true, "num_comments": 6, "num_crossposts": 0, "over_18": false, "parent_whitelist_status": "all_ads", "permalink": "/r/stocks/comments/8oet2e/advice_on_buying_a_stock_with_very_little_info/", "pinned": false, "pwls": 6, "retrieved_on": 1528089354, "rte_mode": "richtext", "score": 0, "selftext": "Excuse my inexperience, but I am looking to buy an inexpensive stock this morning when the markets open and although I know a lot of positive things about this biopharma co. &amp; tomorrow they'll be making a big announcement about something in the pipeline \\(Stage III testing for an Ebola cure has been approved\\).  However, I've searched everywhere for predictions and analysis \\(I'm not at the stage where I can do it myself thoroughly\\), and I'm coming up empty\\-handed.  They have several promising patents for drugs in late stages of approval for things such as Crohn's Disease &amp; IBS.  Would you risk it without expert advice?  At noon they are announcing the Ebola approval, so I want to buy first thing.  What do you think?", "send_replies": true, "spoiler": false, "stickied": false, "subreddit": "stocks", "subreddit_id": "t5_2qjfk", "subreddit_subscribers": 240861, "subreddit_type": "public", "thumbnail": "self", "title": "Advice on buying a stock with very little info avail", "url": "https://www.reddit.com/r/stocks/comments/8oet2e/advice_on_buying_a_stock_with_very_little_info/", "whitelist_status": "all_ads", "wls": 6}, {"author": "ArtisticProgrammer", "author_flair_css_class": null, "author_flair_richtext": [], "author_flair_text": null, "author_flair_type": "text", "can_mod_post": false, "contest_mode": false, "created_utc": 1528164312, "domain": "self.stocks", "full_link": "https://www.reddit.com/r/stocks/comments/8on301/what_will_the_market_do_if_trump_is_indicted/", "gilded": 0, "id": "8on301", "is_crosspostable": true, "is_original_content": false, "is_reddit_media_domain": false, "is_self": true, "is_video": false, "link_flair_richtext": [], "link_flair_text_color": "dark", "link_flair_type": "text", "locked": false, "media_only": false, "no_follow": true, "num_comments": 16, "num_crossposts": 0, "over_18": false, "parent_whitelist_status": "all_ads", "permalink": "/r/stocks/comments/8on301/what_will_the_market_do_if_trump_is_indicted/", "pinned": false, "pwls": 6, "retrieved_on": 1528164314, "rte_mode": "markdown", "score": 0, "selftext": "Starting to look like a genuine possibility now. How to be prepared?", "send_replies": true, "spoiler": false, "stickied": false, "subreddit": "stocks", "subreddit_id": "t5_2qjfk", "subreddit_subscribers": 241048, "subreddit_type": "public", "thumbnail": "self", "title": "What will the market do if Trump is indicted?", "url": "https://www.reddit.com/r/stocks/comments/8on301/what_will_the_market_do_if_trump_is_indicted/", "whitelist_status": "all_ads", "wls": 6}, {"author": "Losingmoneyrightleft", "author_flair_css_class": null, "author_flair_richtext": [], "author_flair_text": null, "author_flair_type": "text", "can_mod_post": false, "contest_mode": false, "created_utc": 1528141545, "domain": "self.stocks", "full_link": "https://www.reddit.com/r/stocks/comments/8ok9lw/time_to_buy_put_on_mu/", "gilded": 0, "id": "8ok9lw", "is_crosspostable": true, "is_original_content": false, "is_reddit_media_domain": false, "is_self": true, "is_video": false, "link_flair_richtext": [], "link_flair_text_color": "dark", "link_flair_type": "text", "locked": false, "media_only": false, "no_follow": true, "num_comments": 25, "num_crossposts": 0, "over_18": false, "parent_whitelist_status": "all_ads", "permalink": "/r/stocks/comments/8ok9lw/time_to_buy_put_on_mu/", "pinned": false, "pwls": 6, "retrieved_on": 1528141546, "rte_mode": "markdown", "score": 0, "selftext": "Closing green on a flat market with the China investigation mess, with flat to red market this week mu is gonna shit itself back to $55 by the end of this week\n\nYou have my word and my word is my bond", "send_replies": true, "spoiler": false, "stickied": false, "subreddit": "stocks", "subreddit_id": "t5_2qjfk", "subreddit_subscribers": 240961, "subreddit_type": "public", "thumbnail": "self", "title": "Time to buy put on MU", "url": "https://www.reddit.com/r/stocks/comments/8ok9lw/time_to_buy_put_on_mu/", "whitelist_status": "all_ads", "wls": 6}, {"author": "LukeB515", "author_flair_css_class": null, "author_flair_richtext": [], "author_flair_text": null, "author_flair_type": "text", "can_mod_post": false, "contest_mode": false, "created_utc": 1528093999, "domain": "self.stocks", "full_link": "https://www.reddit.com/r/stocks/comments/8of6u9/any_tips_for_starting_off_in_investing_and_trading/", "gilded": 0, "id": "8of6u9", "is_crosspostable": true, "is_original_content": false, "is_reddit_media_domain": false, "is_self": true, "is_video": false, "link_flair_background_color": "", "link_flair_css_class": "advice", "link_flair_richtext": [{"e": "text", "t": "Advice"}], "link_flair_template_id": "823be0a6-65e6-11e5-9784-125ee764bc01", "link_flair_text": "Advice", "link_flair_text_color": "dark", "link_flair_type": "richtext", "locked": false, "media_only": false, "no_follow": true, "num_comments": 8, "num_crossposts": 0, "over_18": false, "parent_whitelist_status": "all_ads", "permalink": "/r/stocks/comments/8of6u9/any_tips_for_starting_off_in_investing_and_trading/", "pinned": false, "pwls": 6, "retrieved_on": 1528094000, "rte_mode": "markdown", "score": 0, "selftext": "Also, which sites/apps are the best to use to buy, sell, and trade?", "send_replies": true, "spoiler": false, "stickied": false, "subreddit": "stocks", "subreddit_id": "t5_2qjfk", "subreddit_subscribers": 240874, "subreddit_type": "public", "thumbnail": "self", "title": "Any tips for starting off in investing and trading?", "url": "https://www.reddit.com/r/stocks/comments/8of6u9/any_tips_for_starting_off_in_investing_and_trading/", "whitelist_status": "all_ads", "wls": 6}]