[{"author": "Throwaway_up_in2_sky", "author_flair_css_class": null, "author_flair_richtext": [], "author_flair_text": null, "author_flair_type": "text", "author_fullname": "t2_26cohpuv", "can_mod_post": false, "contest_mode": false, "created_utc": 1536594962, "domain": "self.stocks", "full_link": "https://www.reddit.com/r/stocks/comments/9eoe6q/will_amazoncom_start_selling_new_cars/", "gilded": 0, "id": "9eoe6q", "is_crosspostable": true, "is_meta": false, "is_original_content": false, "is_reddit_media_domain": false, "is_self": true, "is_video": false, "link_flair_background_color": "", "link_flair_richtext": [], "link_flair_text_color": "dark", "link_flair_type": "text", "locked": false, "media_only": false, "no_follow": true, "num_comments": 162, "num_crossposts": 0, "over_18": false, "parent_whitelist_status": "all_ads", "permalink": "/r/stocks/comments/9eoe6q/will_amazoncom_start_selling_new_cars/", "pinned": false, "pwls": 6, "retrieved_on": 1536594963, "score": 194, "selftext": "Amazon.com should start selling new cars.  I hate buying a car from a dealer.  Maybe everyone feels that way.  It would be so nice to shop online, choose the exact options I want, and then buy and have the car delivered.", "send_replies": true, "spoiler": false, "stickied": false, "subreddit": "stocks", "subreddit_id": "t5_2qjfk", "subreddit_subscribers": 269084, "subreddit_type": "public", "thumbnail": "self", "title": "Will Amazon.com start selling new cars?", "url": "https://www.reddit.com/r/stocks/comments/9eoe6q/will_amazoncom_start_selling_new_cars/", "whitelist_status": "all_ads", "wls": 6}, {"author": "cidadefalcao", "author_flair_css_class": null, "author_flair_richtext": [], "author_flair_text": null, "author_flair_type": "text", "author_fullname": "t2_ukrxeun", "can_mod_post": false, "contest_mode": false, "created_utc": 1536566399, "domain": "self.stocks", "full_link": "https://www.reddit.com/r/stocks/comments/9ekz2r/seekingalpha_the_riskreward_of_owning_a_1/", "gilded": 0, "id": "9ekz2r", "is_crosspostable": true, "is_meta": false, "is_original_content": false, "is_reddit_media_domain": false, "is_self": true, "is_video": false, "link_flair_background_color": "", "link_flair_richtext": [], "link_flair_text_color": "dark", "link_flair_type": "text", "locked": false, "media_only": false, "no_follow": true, "num_comments": 85, "num_crossposts": 0, "over_18": false, "parent_whitelist_status": "all_ads", "permalink": "/r/stocks/comments/9ekz2r/seekingalpha_the_riskreward_of_owning_a_1/", "pinned": false, "pwls": 6, "retrieved_on": 1536566399, "score": 87, "selftext": "[http://www.thefinancist.com/results\\_article/?article\\_id=5231410544192262](http://www.thefinancist.com/results_article/?article_id=5231410544192262)\n\n## Summary\n\nAmazon has been in an extended bull market for nearly two decades.\n\nExtended bull markets obscure logic, causing price and value to become irrelevant as investors chase momentum.\n\nCongratulations to Amazon bulls on your successes so far, but to actually buy AMZN stock at a $1 trillion valuation makes absolutely no sense.\n\n\\_\\_\\_\\_\\_\\_\\_\\_\\_\\_\\_\\_\\_\\_\\_\\_\\_\\_\\_\\_\\_\\_\\_\\_\\_\\_\\_\\_\\_\\_\n\nthoughts?", "send_replies": true, "spoiler": false, "stickied": false, "subreddit": "stocks", "subreddit_id": "t5_2qjfk", "subreddit_subscribers": 268982, "subreddit_type": "public", "thumbnail": "self", "title": "SeekingAlpha: The Risk/Reward Of Owning A $1 Trillion Amazon Is Terrible", "url": "https://www.reddit.com/r/stocks/comments/9ekz2r/seekingalpha_the_riskreward_of_owning_a_1/", "whitelist_status": "all_ads", "wls": 6}, {"author": "portajohnjackoff", "author_flair_css_class": null, "author_flair_richtext": [], "author_flair_text": null, "author_flair_type": "text", "author_fullname": "t2_fzl83", "can_mod_post": false, "contest_mode": false, "created_utc": 1536598423, "domain": "self.stocks", "full_link": "https://www.reddit.com/r/stocks/comments/9eowj0/biggest_loser/", "gilded": 0, "id": "9eowj0", "is_crosspostable": true, "is_meta": false, "is_original_content": false, "is_reddit_media_domain": false, "is_self": true, "is_video": false, "link_flair_background_color": "", "link_flair_richtext": [], "link_flair_text_color": "dark", "link_flair_type": "text", "locked": false, "media_only": false, "no_follow": true, "num_comments": 96, "num_crossposts": 0, "over_18": false, "parent_whitelist_status": "all_ads", "permalink": "/r/stocks/comments/9eowj0/biggest_loser/", "pinned": false, "pwls": 6, "retrieved_on": 1536598423, "score": 23, "selftext": "What is your bigger loser that you're currently holding, and why are you long on it?", "send_replies": true, "spoiler": false, "stickied": false, "subreddit": "stocks", "subreddit_id": "t5_2qjfk", "subreddit_subscribers": 269102, "subreddit_type": "public", "thumbnail": "self", "title": "Biggest loser", "url": "https://www.reddit.com/r/stocks/comments/9eowj0/biggest_loser/", "whitelist_status": "all_ads", "wls": 6}, {"author": "happytravelbug", "author_flair_css_class": null, "author_flair_richtext": [], "author_flair_text": null, "author_flair_type": "text", "author_fullname": "t2_1a22ctz8", "can_mod_post": false, "contest_mode": false, "created_utc": 1536622227, "domain": "self.stocks", "full_link": "https://www.reddit.com/r/stocks/comments/9es924/good_high_growth_stocks_to_broaden_portfolio/", "gilded": 0, "id": "9es924", "is_crosspostable": true, "is_meta": false, "is_original_content": false, "is_reddit_media_domain": false, "is_self": true, "is_video": false, "link_flair_background_color": "", "link_flair_richtext": [], "link_flair_text_color": "dark", "link_flair_type": "text", "locked": false, "media_only": false, "no_follow": true, "num_comments": 67, "num_crossposts": 0, "over_18": false, "parent_whitelist_status": "all_ads", "permalink": "/r/stocks/comments/9es924/good_high_growth_stocks_to_broaden_portfolio/", "pinned": false, "pwls": 6, "retrieved_on": 1536622229, "score": 18, "selftext": "Currently holding (from largest to smallest holdings values as of today): Amazon (25%), Square (12%), Nvidia (10%), Stitch Fix (10%), Microsoft (8%), Salesforce (8%), Google (6%),  Alibaba (6%), Grubhub (4%), Paypal (3%) and remaining ~8% in a Fidelity S&amp;P 500 based mutual fund.\n\nWhat should I buy next? My portfolio is worth 85K and I got another 50K in cash just sitting now for the last year in anticipatioin of a crash. That makes me feel stupid.\n\n I have also made stupid mistakes selling netflix, amd and apple all at low or no profit because I got spooked but I'm becoming more disciplined now and want to find more good picks that can double or triple their value within the next 2 years.", "send_replies": true, "spoiler": false, "stickied": false, "subreddit": "stocks", "subreddit_id": "t5_2qjfk", "subreddit_subscribers": 269226, "subreddit_type": "public", "thumbnail": "self", "title": "Good high growth stocks to broaden portfolio?", "url": "https://www.reddit.com/r/stocks/comments/9es924/good_high_growth_stocks_to_broaden_portfolio/", "whitelist_status": "all_ads", "wls": 6}, {"author": "digitalradiohead", "author_flair_css_class": null, "author_flair_richtext": [], "author_flair_text": null, "author_flair_type": "text", "author_fullname": "t2_8k3dc", "can_mod_post": false, "contest_mode": false, "created_utc": 1536566629, "domain": "self.stocks", "full_link": "https://www.reddit.com/r/stocks/comments/9ekzx4/clorox_or_pepsi/", "gilded": 0, "id": "9ekzx4", "is_crosspostable": true, "is_meta": false, "is_original_content": false, "is_reddit_media_domain": false, "is_self": true, "is_video": false, "link_flair_background_color": "", "link_flair_richtext": [], "link_flair_text_color": "dark", "link_flair_type": "text", "locked": false, "media_only": false, "no_follow": true, "num_comments": 16, "num_crossposts": 0, "over_18": false, "parent_whitelist_status": "all_ads", "permalink": "/r/stocks/comments/9ekzx4/clorox_or_pepsi/", "pinned": false, "pwls": 6, "retrieved_on": 1536566631, "score": 13, "selftext": "Looking at buying staples here. Clorox looks the best to me but it is sitting right at it's all time high. Pepsi on the otherhand pulled back and for good reason. They lost a very good CEO. I do like that both companies are buying back shares like crazy and sales are growing. Both have decent margins as well. One thing that worries me about pepsi is the decline in soda sales. I know they are diversified but that is still a big chunk of revenue for them. Clorox product line doesn't see as many shifts in trends and seems like a solid bet. What do you guys think?", "send_replies": true, "spoiler": false, "stickied": false, "subreddit": "stocks", "subreddit_id": "t5_2qjfk", "subreddit_subscribers": 268982, "subreddit_type": "public", "thumbnail": "self", "title": "Clorox or Pepsi?", "url": "https://www.reddit.com/r/stocks/comments/9ekzx4/clorox_or_pepsi/", "whitelist_status": "all_ads", "wls": 6}, {"author": "Strucksen", "author_flair_css_class": null, "author_flair_richtext": [], "author_flair_text": null, "author_flair_type": "text", "author_fullname": "t2_po9y3", "can_mod_post": false, "contest_mode": false, "created_utc": 1536565000, "domain": "self.stocks", "full_link": "https://www.reddit.com/r/stocks/comments/9ekucd/what_do_you_think_of_danske_bank/", "gilded": 0, "id": "9ekucd", "is_crosspostable": true, "is_meta": false, "is_original_content": false, "is_reddit_media_domain": false, "is_self": true, "is_video": false, "link_flair_background_color": "", "link_flair_richtext": [], "link_flair_text_color": "dark", "link_flair_type": "text", "locked": false, "media_only": false, "no_follow": true, "num_comments": 8, "num_crossposts": 0, "over_18": false, "parent_whitelist_status": "all_ads", "permalink": "/r/stocks/comments/9ekucd/what_do_you_think_of_danske_bank/", "pinned": false, "pwls": 6, "retrieved_on": 1536565000, "score": 13, "selftext": "They are a Danish Bank that has white washed money for some Russian Companies. That of course made the shares price fall. But because they are so low. Should i Invest. Im thinking that just because they white washed money doesn't mean that they will make less money, right?", "send_replies": true, "spoiler": false, "stickied": false, "subreddit": "stocks", "subreddit_id": "t5_2qjfk", "subreddit_subscribers": 268975, "subreddit_type": "public", "thumbnail": "self", "title": "What do you think of Danske Bank", "url": "https://www.reddit.com/r/stocks/comments/9ekucd/what_do_you_think_of_danske_bank/", "whitelist_status": "all_ads", "wls": 6}, {"author": "CopperTrophy", "author_flair_css_class": null, "author_flair_richtext": [], "author_flair_text": null, "author_flair_type": "text", "author_fullname": "t2_s8h7z", "can_mod_post": false, "contest_mode": false, "created_utc": 1536621747, "domain": "self.stocks", "full_link": "https://www.reddit.com/r/stocks/comments/9es6zz/if_a_stock_is_worth_200_and_you_expect_the_stock/", "gilded": 0, "id": "9es6zz", "is_crosspostable": true, "is_meta": false, "is_original_content": false, "is_reddit_media_domain": false, "is_self": true, "is_video": false, "link_flair_background_color": "", "link_flair_richtext": [], "link_flair_text_color": "dark", "link_flair_type": "text", "locked": false, "media_only": false, "no_follow": true, "num_comments": 5, "num_crossposts": 0, "over_18": false, "parent_whitelist_status": "all_ads", "permalink": "/r/stocks/comments/9es6zz/if_a_stock_is_worth_200_and_you_expect_the_stock/", "pinned": false, "pwls": 6, "retrieved_on": 1536621748, "score": 7, "selftext": "I am not sure at what price to buy a put or buy a call. Is there any systematic way of doing this?", "send_replies": true, "spoiler": false, "stickied": false, "subreddit": "stocks", "subreddit_id": "t5_2qjfk", "subreddit_subscribers": 269223, "subreddit_type": "public", "thumbnail": "self", "title": "If a stock is worth 200 and you expect the stock to go to 100 you buy a 200$ put, and you buy a 200$ call if you expect it to go to 300$?", "url": "https://www.reddit.com/r/stocks/comments/9es6zz/if_a_stock_is_worth_200_and_you_expect_the_stock/", "whitelist_status": "all_ads", "wls": 6}, {"author": "ht019", "author_flair_css_class": null, "author_flair_richtext": [], "author_flair_text": null, "author_flair_type": "text", "author_fullname": "t2_1ezde78s", "can_mod_post": false, "contest_mode": false, "created_utc": 1536581585, "domain": "self.stocks", "full_link": "https://www.reddit.com/r/stocks/comments/9emjgd/nlst/", "gilded": 0, "id": "9emjgd", "is_crosspostable": true, "is_meta": false, "is_original_content": false, "is_reddit_media_domain": false, "is_self": true, "is_video": false, "link_flair_background_color": "", "link_flair_richtext": [], "link_flair_text_color": "dark", "link_flair_type": "text", "locked": false, "media_only": false, "no_follow": true, "num_comments": 13, "num_crossposts": 0, "over_18": false, "parent_whitelist_status": "all_ads", "permalink": "/r/stocks/comments/9emjgd/nlst/", "pinned": false, "pwls": 6, "retrieved_on": 1536581586, "score": 6, "selftext": "Saw a huge jump but wondering if it\u2019s too late to buy?", "send_replies": true, "spoiler": false, "stickied": false, "subreddit": "stocks", "subreddit_id": "t5_2qjfk", "subreddit_subscribers": 269001, "subreddit_type": "public", "thumbnail": "self", "title": "NLST", "url": "https://www.reddit.com/r/stocks/comments/9emjgd/nlst/", "whitelist_status": "all_ads", "wls": 6}, {"author": "CSGORevolverDev", "author_flair_css_class": null, "author_flair_richtext": [], "author_flair_text": null, "author_flair_type": "text", "author_fullname": "t2_st4ba", "can_mod_post": false, "contest_mode": false, "created_utc": 1536611027, "domain": "self.stocks", "full_link": "https://www.reddit.com/r/stocks/comments/9eqqde/thoughts_on_logi/", "gilded": 0, "id": "9eqqde", "is_crosspostable": true, "is_meta": false, "is_original_content": false, "is_reddit_media_domain": false, "is_self": true, "is_video": false, "link_flair_background_color": "", "link_flair_richtext": [], "link_flair_text_color": "dark", "link_flair_type": "text", "locked": false, "media_only": false, "no_follow": true, "num_comments": 6, "num_crossposts": 0, "over_18": false, "parent_whitelist_status": "all_ads", "permalink": "/r/stocks/comments/9eqqde/thoughts_on_logi/", "pinned": false, "pwls": 6, "retrieved_on": 1536611028, "score": 6, "selftext": "I actually haven\u2019t heard them being mentioned much yet I feel like they\u2019re actually quite popular in the gaming industry. I have a gaming mouse from them, and am wondering what you guys think about Logitech. Did something happen to them in the past which is making people not trade Logitech stocks?", "send_replies": true, "spoiler": false, "stickied": false, "subreddit": "stocks", "subreddit_id": "t5_2qjfk", "subreddit_subscribers": 269158, "subreddit_type": "public", "thumbnail": "self", "title": "Thoughts on LOGI?", "url": "https://www.reddit.com/r/stocks/comments/9eqqde/thoughts_on_logi/", "whitelist_status": "all_ads", "wls": 6}, {"author": "FieldGreen85", "author_flair_css_class": null, "author_flair_richtext": [], "author_flair_text": null, "author_flair_type": "text", "author_fullname": "t2_e25bu", "can_mod_post": false, "contest_mode": false, "created_utc": 1536631595, "domain": "self.stocks", "full_link": "https://www.reddit.com/r/stocks/comments/9etdeu/sg_blocks_residential/", "gilded": 0, "id": "9etdeu", "is_crosspostable": true, "is_meta": false, "is_original_content": false, "is_reddit_media_domain": false, "is_self": true, "is_video": false, "link_flair_background_color": "", "link_flair_richtext": [], "link_flair_text_color": "dark", "link_flair_type": "text", "locked": false, "media_only": false, "no_follow": true, "num_comments": 1, "num_crossposts": 0, "over_18": false, "parent_whitelist_status": "all_ads", "permalink": "/r/stocks/comments/9etdeu/sg_blocks_residential/", "pinned": false, "pwls": 6, "retrieved_on": 1536631596, "score": 5, "selftext": "Thought I would share! Disclaimer: I own a ton of this company.\n\nhttps://finance.yahoo.com/news/sg-blocks-partners-senior-financial-123000144.html?.tsrc=applewf", "send_replies": true, "spoiler": false, "stickied": false, "subreddit": "stocks", "subreddit_id": "t5_2qjfk", "subreddit_subscribers": 269266, "subreddit_type": "public", "thumbnail": "self", "title": "SG Blocks - Residential", "url": "https://www.reddit.com/r/stocks/comments/9etdeu/sg_blocks_residential/", "whitelist_status": "all_ads", "wls": 6}, {"author": "purplenalgene17", "author_flair_css_class": null, "author_flair_richtext": [], "author_flair_text": null, "author_flair_type": "text", "author_fullname": "t2_23tu6dq3", "can_mod_post": false, "contest_mode": false, "created_utc": 1536613167, "domain": "self.stocks", "full_link": "https://www.reddit.com/r/stocks/comments/9er1ga/anyone_buying_trxc/", "gilded": 0, "id": "9er1ga", "is_crosspostable": true, "is_meta": false, "is_original_content": false, "is_reddit_media_domain": false, "is_self": true, "is_video": false, "link_flair_background_color": "", "link_flair_richtext": [], "link_flair_text_color": "dark", "link_flair_type": "text", "locked": false, "media_only": false, "no_follow": true, "num_comments": 23, "num_crossposts": 0, "over_18": false, "parent_whitelist_status": "all_ads", "permalink": "/r/stocks/comments/9er1ga/anyone_buying_trxc/", "pinned": false, "pwls": 6, "retrieved_on": 1536613168, "score": 5, "selftext": "I\u2019m thinking about buying some TRXC. Anyone buying this dip and if so, when? Thanks! ", "send_replies": true, "spoiler": false, "stickied": false, "subreddit": "stocks", "subreddit_id": "t5_2qjfk", "subreddit_subscribers": 269171, "subreddit_type": "public", "thumbnail": "self", "title": "Anyone buying TRXC?", "url": "https://www.reddit.com/r/stocks/comments/9er1ga/anyone_buying_trxc/", "whitelist_status": "all_ads", "wls": 6}, {"author": "MychaelH", "author_flair_css_class": null, "author_flair_richtext": [], "author_flair_text": null, "author_flair_type": "text", "author_fullname": "t2_x5vgq", "can_mod_post": false, "contest_mode": false, "created_utc": 1536589369, "domain": "self.stocks", "full_link": "https://www.reddit.com/r/stocks/comments/9enkmc/msft_and_nvda_buy_now_or_wait/", "gilded": 0, "id": "9enkmc", "is_crosspostable": true, "is_meta": false, "is_original_content": false, "is_reddit_media_domain": false, "is_self": true, "is_video": false, "link_flair_background_color": "", "link_flair_richtext": [], "link_flair_text_color": "dark", "link_flair_type": "text", "locked": false, "media_only": false, "no_follow": true, "num_comments": 18, "num_crossposts": 0, "over_18": false, "parent_whitelist_status": "all_ads", "permalink": "/r/stocks/comments/9enkmc/msft_and_nvda_buy_now_or_wait/", "pinned": false, "pwls": 6, "retrieved_on": 1536589371, "score": 5, "selftext": "Thoughts? I bought NVDA pretty late and have been watching MSFT for a week now. ", "send_replies": true, "spoiler": false, "stickied": false, "subreddit": "stocks", "subreddit_id": "t5_2qjfk", "subreddit_subscribers": 269049, "subreddit_type": "public", "thumbnail": "self", "title": "MSFT AND NVDA buy now or wait?", "url": "https://www.reddit.com/r/stocks/comments/9enkmc/msft_and_nvda_buy_now_or_wait/", "whitelist_status": "all_ads", "wls": 6}, {"author": "JeremyMcG1", "author_flair_css_class": null, "author_flair_richtext": [], "author_flair_text": null, "author_flair_type": "text", "author_fullname": "t2_10tzdc", "can_mod_post": false, "contest_mode": false, "created_utc": 1536612192, "domain": "self.stocks", "full_link": "https://www.reddit.com/r/stocks/comments/9eqwg8/companies_paying_companies_in_stock/", "gilded": 0, "id": "9eqwg8", "is_crosspostable": true, "is_meta": false, "is_original_content": false, "is_reddit_media_domain": false, "is_self": true, "is_video": false, "link_flair_background_color": "", "link_flair_richtext": [], "link_flair_text_color": "dark", "link_flair_type": "text", "locked": false, "media_only": false, "no_follow": true, "num_comments": 9, "num_crossposts": 0, "over_18": false, "parent_whitelist_status": "all_ads", "permalink": "/r/stocks/comments/9eqwg8/companies_paying_companies_in_stock/", "pinned": false, "pwls": 6, "retrieved_on": 1536612192, "score": 4, "selftext": "Curious question here:  Does anyone know (worldwide) if there are B2B groups that transfer value for goods and services rendered company to company - but instead of using fiat, they pay the seller in stock?  ", "send_replies": true, "spoiler": false, "stickied": false, "subreddit": "stocks", "subreddit_id": "t5_2qjfk", "subreddit_subscribers": 269167, "subreddit_type": "public", "thumbnail": "self", "title": "Companies paying companies in stock?", "url": "https://www.reddit.com/r/stocks/comments/9eqwg8/companies_paying_companies_in_stock/", "whitelist_status": "all_ads", "wls": 6}, {"author": "xenocloud1989", "author_flair_css_class": null, "author_flair_richtext": [], "author_flair_text": null, "author_flair_type": "text", "author_fullname": "t2_ym36i", "can_mod_post": false, "contest_mode": false, "created_utc": 1536595962, "domain": "self.stocks", "full_link": "https://www.reddit.com/r/stocks/comments/9eojhu/is_tcehy_still_a_healthy_company/", "gilded": 0, "id": "9eojhu", "is_crosspostable": true, "is_meta": false, "is_original_content": false, "is_reddit_media_domain": false, "is_self": true, "is_video": false, "link_flair_background_color": "", "link_flair_richtext": [], "link_flair_text_color": "dark", "link_flair_type": "text", "locked": false, "media_only": false, "no_follow": true, "num_comments": 22, "num_crossposts": 0, "over_18": false, "parent_whitelist_status": "all_ads", "permalink": "/r/stocks/comments/9eojhu/is_tcehy_still_a_healthy_company/", "pinned": false, "pwls": 6, "retrieved_on": 1536595962, "score": 4, "selftext": "I am not asking about the stock price. My investment in TCEHY make me lose a lot. But I still want to learn whether this is a healthy company which will grow in the future.\n\nThe Chinese regulation on gaming makes me really nervous. Other than WECHAT, does it still have other products/ investment?", "send_replies": true, "spoiler": false, "stickied": false, "subreddit": "stocks", "subreddit_id": "t5_2qjfk", "subreddit_subscribers": 269089, "subreddit_type": "public", "thumbnail": "self", "title": "Is TCEHY still a healthy company?", "url": "https://www.reddit.com/r/stocks/comments/9eojhu/is_tcehy_still_a_healthy_company/", "whitelist_status": "all_ads", "wls": 6}, {"author": "McCarty898", "author_flair_css_class": null, "author_flair_richtext": [], "author_flair_text": null, "author_flair_type": "text", "author_fullname": "t2_oc6itnb", "can_mod_post": false, "contest_mode": false, "created_utc": 1536604662, "domain": "self.stocks", "full_link": "https://www.reddit.com/r/stocks/comments/9ept2a/atvi_today/", "gilded": 0, "id": "9ept2a", "is_crosspostable": true, "is_meta": false, "is_original_content": false, "is_reddit_media_domain": false, "is_self": true, "is_video": false, "link_flair_background_color": "", "link_flair_richtext": [], "link_flair_text_color": "dark", "link_flair_type": "text", "locked": false, "media_only": false, "no_follow": true, "num_comments": 2, "num_crossposts": 0, "over_18": false, "parent_whitelist_status": "all_ads", "permalink": "/r/stocks/comments/9ept2a/atvi_today/", "pinned": false, "pwls": 6, "retrieved_on": 1536604663, "score": 3, "selftext": "Any ideas why ATVI is doing well today compared to EA and TTWO? Normally I see them moving in tandem.", "send_replies": true, "spoiler": false, "stickied": false, "subreddit": "stocks", "subreddit_id": "t5_2qjfk", "subreddit_subscribers": 269129, "subreddit_type": "public", "thumbnail": "self", "title": "ATVI Today", "url": "https://www.reddit.com/r/stocks/comments/9ept2a/atvi_today/", "whitelist_status": "all_ads", "wls": 6}, {"author": "Mhobbers", "author_flair_css_class": null, "author_flair_richtext": [], "author_flair_text": null, "author_flair_type": "text", "author_fullname": "t2_kmhum", "can_mod_post": false, "contest_mode": false, "created_utc": 1536626496, "domain": "self.stocks", "full_link": "https://www.reddit.com/r/stocks/comments/9esrtf/mu_stock/", "gilded": 0, "id": "9esrtf", "is_crosspostable": true, "is_meta": false, "is_original_content": false, "is_reddit_media_domain": false, "is_self": true, "is_video": false, "link_flair_background_color": "", "link_flair_richtext": [], "link_flair_text_color": "dark", "link_flair_type": "text", "locked": false, "media_only": false, "no_follow": true, "num_comments": 27, "num_crossposts": 0, "over_18": false, "parent_whitelist_status": "all_ads", "permalink": "/r/stocks/comments/9esrtf/mu_stock/", "pinned": false, "pwls": 6, "retrieved_on": 1536626497, "score": 3, "selftext": "Why did MU go down so much when their price target was lowered? 75 dollars is still massive gains..... ", "send_replies": true, "spoiler": false, "stickied": false, "subreddit": "stocks", "subreddit_id": "t5_2qjfk", "subreddit_subscribers": 269243, "subreddit_type": "public", "thumbnail": "self", "title": "MU stock", "url": "https://www.reddit.com/r/stocks/comments/9esrtf/mu_stock/", "whitelist_status": "all_ads", "wls": 6}, {"author": "Psychic_Bias", "author_flair_css_class": null, "author_flair_richtext": [], "author_flair_text": null, "author_flair_type": "text", "author_fullname": "t2_1bmbsa23", "can_mod_post": false, "contest_mode": false, "created_utc": 1536607979, "domain": "self.stocks", "full_link": "https://www.reddit.com/r/stocks/comments/9eqa95/buying_at_market_value/", "gilded": 0, "id": "9eqa95", "is_crosspostable": true, "is_meta": false, "is_original_content": false, "is_reddit_media_domain": false, "is_self": true, "is_video": false, "link_flair_background_color": "", "link_flair_richtext": [], "link_flair_text_color": "dark", "link_flair_type": "text", "locked": false, "media_only": false, "no_follow": true, "num_comments": 4, "num_crossposts": 0, "over_18": false, "parent_whitelist_status": "all_ads", "permalink": "/r/stocks/comments/9eqa95/buying_at_market_value/", "pinned": false, "pwls": 6, "retrieved_on": 1536607980, "score": 2, "selftext": "I follow a number of different investing subreddits and discord\u2019s (trying my best to learn as much as possible), and something I\u2019ve seen mentioned multiple times is the advice: \u201cyou shouldn\u2019t purchase a stock at market value.\u201d\n\nDoes this mean I should be buying calls instead? ", "send_replies": true, "spoiler": false, "stickied": false, "subreddit": "stocks", "subreddit_id": "t5_2qjfk", "subreddit_subscribers": 269140, "subreddit_type": "public", "thumbnail": "self", "title": "Buying at market value", "url": "https://www.reddit.com/r/stocks/comments/9eqa95/buying_at_market_value/", "whitelist_status": "all_ads", "wls": 6}, {"author": "JimmyD4294", "author_flair_css_class": null, "author_flair_richtext": [], "author_flair_text": null, "author_flair_type": "text", "author_fullname": "t2_14uvy9", "can_mod_post": false, "contest_mode": false, "created_utc": 1536613670, "domain": "self.stocks", "full_link": "https://www.reddit.com/r/stocks/comments/9er43j/call_option_on_mu_to_reach_50/", "gilded": 0, "id": "9er43j", "is_crosspostable": true, "is_meta": false, "is_original_content": false, "is_reddit_media_domain": false, "is_self": true, "is_video": false, "link_flair_background_color": "", "link_flair_richtext": [], "link_flair_text_color": "dark", "link_flair_type": "text", "locked": false, "media_only": false, "no_follow": true, "num_comments": 6, "num_crossposts": 0, "over_18": false, "parent_whitelist_status": "all_ads", "permalink": "/r/stocks/comments/9er43j/call_option_on_mu_to_reach_50/", "pinned": false, "pwls": 6, "retrieved_on": 1536613671, "score": 2, "selftext": "I'm not in doubt that MU will reach back to $50 I just don't know how long it'll take and if I should take this as an advantage to buy a call for maybe 2 weeks? ", "send_replies": true, "spoiler": false, "stickied": false, "subreddit": "stocks", "subreddit_id": "t5_2qjfk", "subreddit_subscribers": 269178, "subreddit_type": "public", "thumbnail": "self", "title": "Call option on MU to reach $50", "url": "https://www.reddit.com/r/stocks/comments/9er43j/call_option_on_mu_to_reach_50/", "whitelist_status": "all_ads", "wls": 6}, {"author": "AutoModerator", "author_flair_css_class": null, "author_flair_richtext": [], "author_flair_text": null, "author_flair_type": "text", "author_fullname": "t2_6l4z3", "can_mod_post": false, "contest_mode": false, "created_utc": 1536577720, "domain": "self.stocks", "full_link": "https://www.reddit.com/r/stocks/comments/9em3g8/rstocks_daily_discussion_monday_sep_10_2018/", "gilded": 0, "id": "9em3g8", "is_crosspostable": true, "is_meta": false, "is_original_content": false, "is_reddit_media_domain": false, "is_self": true, "is_video": false, "link_flair_background_color": "", "link_flair_richtext": [], "link_flair_text_color": "dark", "link_flair_type": "text", "locked": false, "media_only": false, "no_follow": true, "num_comments": 15, "num_crossposts": 0, "over_18": false, "parent_whitelist_status": "all_ads", "permalink": "/r/stocks/comments/9em3g8/rstocks_daily_discussion_monday_sep_10_2018/", "pinned": false, "pwls": 6, "retrieved_on": 1536577721, "score": 2, "selftext": "These daily discussions run from Monday to Friday and Friday's will stay up till Monday.\n\nSome helpful links:\n\n* [Finviz](https://finviz.com/quote.ashx?t=amd) for charts, fundamentals, and aggregated news\n* StreetInsider news:\n * [Market Check](https://www.streetinsider.com/Market+Check) - Possibly why the market is doing what it's doing\n * [Corporate News](https://www.streetinsider.com/Corporate+News)\n * [Reuters aggregated](https://www.streetinsider.com/Reuters) - Global news\n * [Economic data](https://www.streetinsider.com/Economic+Data)\n * [FED](https://www.streetinsider.com/Fed) - Federal Reserve news\n\nIf you have a basic question, for example \"what is EPS,\" then google \"investopedia EPS\" and click the investopedia article on it; do this for everything until you have a more in depth question or just want to share what you learned.\n\nPlease discuss your portfolios in the [Rate My Portfolio sticky.](https://www.reddit.com/r/stocks/about/sticky) or see past portfolio discussions with [this link.](https://www.reddit.com/r/stocks/search?sort=new&amp;q=Rate+My+Portfolio+-+r%2FStocks+Quarterly+Thread&amp;t=all&amp;restrict_sr=on)\n\nSee past [daily discussions here.](https://www.reddit.com/r/stocks/search?q=author%3Aautomoderator+%22r%2Fstocks+daily+discussion%22&amp;restrict_sr=on&amp;sort=new&amp;t=all)  And use this link to see past stock [options discussions here.](https://www.reddit.com/r/stocks/search?q=author%3Aautomoderator+%22r%2Fstocks+options%22&amp;restrict_sr=on&amp;sort=new&amp;t=all)\n", "send_replies": false, "spoiler": false, "stickied": false, "subreddit": "stocks", "subreddit_id": "t5_2qjfk", "subreddit_subscribers": 268998, "subreddit_type": "public", "suggested_sort": "new", "thumbnail": "self", "title": "r/Stocks Daily Discussion Monday - Sep 10, 2018", "url": "https://www.reddit.com/r/stocks/comments/9em3g8/rstocks_daily_discussion_monday_sep_10_2018/", "whitelist_status": "all_ads", "wls": 6}, {"author": "Other475", "author_flair_css_class": null, "author_flair_richtext": [], "author_flair_text": null, "author_flair_type": "text", "author_fullname": "t2_1joc1odi", "can_mod_post": false, "contest_mode": false, "created_utc": 1536621283, "domain": "self.stocks", "full_link": "https://www.reddit.com/r/stocks/comments/9es4vb/if_you_could_only_invest_in_one_company_cvsi_or/", "gilded": 0, "id": "9es4vb", "is_crosspostable": true, "is_meta": false, "is_original_content": false, "is_reddit_media_domain": false, "is_self": true, "is_video": false, "link_flair_background_color": "", "link_flair_css_class": "advicerequest", "link_flair_richtext": [], "link_flair_template_id": "75a227ec-65e6-11e5-96ee-12d48f46797b", "link_flair_text": "Advice Request", "link_flair_text_color": "dark", "link_flair_type": "text", "locked": false, "media_only": false, "no_follow": true, "num_comments": 5, "num_crossposts": 0, "over_18": false, "parent_whitelist_status": "all_ads", "permalink": "/r/stocks/comments/9es4vb/if_you_could_only_invest_in_one_company_cvsi_or/", "pinned": false, "pwls": 6, "retrieved_on": 1536621284, "score": 2, "selftext": "If you could only invest in one company...\n\n$CVSI or $ACBFF ???", "send_replies": true, "spoiler": false, "stickied": false, "subreddit": "stocks", "subreddit_id": "t5_2qjfk", "subreddit_subscribers": 269218, "subreddit_type": "public", "thumbnail": "self", "title": "If you could only invest in one company... CVSI or ACBFF ???", "url": "https://www.reddit.com/r/stocks/comments/9es4vb/if_you_could_only_invest_in_one_company_cvsi_or/", "whitelist_status": "all_ads", "wls": 6}, {"author": "doggowalko", "author_flair_css_class": null, "author_flair_richtext": [], "author_flair_text": null, "author_flair_type": "text", "author_fullname": "t2_fwgcy9j", "can_mod_post": false, "contest_mode": false, "created_utc": 1536593276, "domain": "self.stocks", "full_link": "https://www.reddit.com/r/stocks/comments/9eo5gh/income_stocks/", "gilded": 0, "id": "9eo5gh", "is_crosspostable": true, "is_meta": false, "is_original_content": false, "is_reddit_media_domain": false, "is_self": true, "is_video": false, "link_flair_background_color": "", "link_flair_richtext": [], "link_flair_text_color": "dark", "link_flair_type": "text", "locked": false, "media_only": false, "no_follow": true, "num_comments": 6, "num_crossposts": 0, "over_18": false, "parent_whitelist_status": "all_ads", "permalink": "/r/stocks/comments/9eo5gh/income_stocks/", "pinned": false, "pwls": 6, "retrieved_on": 1536593277, "score": 2, "selftext": "Any suggestions for income stocks, high dividend to share price ratio?  Particularly securities that will at least hold their value.  I don't want to lose the income to capital losses obviously.  I'd like to diversify my portfolio to include more income stocks.  ", "send_replies": true, "spoiler": false, "stickied": false, "subreddit": "stocks", "subreddit_id": "t5_2qjfk", "subreddit_subscribers": 269070, "subreddit_type": "public", "thumbnail": "self", "title": "Income stocks.", "url": "https://www.reddit.com/r/stocks/comments/9eo5gh/income_stocks/", "whitelist_status": "all_ads", "wls": 6}, {"author": "r3alZillA", "author_flair_css_class": null, "author_flair_richtext": [], "author_flair_text": null, "author_flair_type": "text", "author_fullname": "t2_18wvxjca", "can_mod_post": false, "contest_mode": false, "created_utc": 1536593836, "domain": "self.stocks", "full_link": "https://www.reddit.com/r/stocks/comments/9eo8ew/ktos/", "gilded": 0, "id": "9eo8ew", "is_crosspostable": false, "is_meta": false, "is_original_content": false, "is_reddit_media_domain": false, "is_self": true, "is_video": false, "link_flair_background_color": "", "link_flair_richtext": [], "link_flair_text_color": "dark", "link_flair_type": "text", "locked": false, "media_only": false, "no_follow": true, "num_comments": 1, "num_crossposts": 0, "over_18": false, "parent_whitelist_status": "all_ads", "permalink": "/r/stocks/comments/9eo8ew/ktos/", "pinned": false, "pwls": 6, "retrieved_on": 1536593838, "score": 1, "selftext": "[removed]", "send_replies": true, "spoiler": false, "stickied": false, "subreddit": "stocks", "subreddit_id": "t5_2qjfk", "subreddit_subscribers": 269074, "subreddit_type": "public", "thumbnail": "self", "title": "KTOS", "url": "https://www.reddit.com/r/stocks/comments/9eo8ew/ktos/", "whitelist_status": "all_ads", "wls": 6}, {"author": "Skyrs9", "author_flair_css_class": null, "author_flair_richtext": [], "author_flair_text": null, "author_flair_type": "text", "author_fullname": "t2_3k4uxoe", "can_mod_post": false, "contest_mode": false, "created_utc": 1536594603, "domain": "self.stocks", "full_link": "https://www.reddit.com/r/stocks/comments/9eoceb/bayn_good_time_to_buy/", "gilded": 0, "id": "9eoceb", "is_crosspostable": true, "is_meta": false, "is_original_content": false, "is_reddit_media_domain": false, "is_self": true, "is_video": false, "link_flair_background_color": "", "link_flair_css_class": "question", "link_flair_richtext": [], "link_flair_template_id": "8f98f5d6-65e6-11e5-a4a5-125ee764bc01", "link_flair_text": "Question", "link_flair_text_color": "dark", "link_flair_type": "text", "locked": false, "media_only": false, "no_follow": true, "num_comments": 5, "num_crossposts": 0, "over_18": false, "parent_whitelist_status": "all_ads", "permalink": "/r/stocks/comments/9eoceb/bayn_good_time_to_buy/", "pinned": false, "pwls": 6, "retrieved_on": 1536594603, "score": 1, "selftext": "Bayer shares are currently experiencing a fall in price right now (currently at \u20ac72.69) because of the whole Monsanto court case. However I believe that investors have been too bearish and have overreacted. \n\n\n\nI\u2019ve been reading up on some forecasts:\n\n\u201cThe 25 analysts offering 12 month price targets for Bayer AG have a median target of 100.00, with a high estimate of 127.93 and a low estimate of 80.00. The median estimate represents a 36.07% increase from the last price of 73.49.\u201d\n\n- Bayer (BAYN) Given a \u20ac105.00 Price Target at Barclays\n\n- Bayer (FRA:BAYN) PT Set at \u20ac130.00 by Deutsche Bank\n\n- Bayer (BAYN) PT Set at \u20ac95.00 by Credit Suisse Group\n\n- Bayer (BAYN) PT Set at \u20ac130.00 by UBS Group\n\n- JPMorgan Chase &amp; Co. Reaffirms \u201cBuy\u201d Rating for Bayer ", "send_replies": true, "spoiler": false, "stickied": false, "subreddit": "stocks", "subreddit_id": "t5_2qjfk", "subreddit_subscribers": 269079, "subreddit_type": "public", "thumbnail": "self", "title": "BAYN - good time to buy?", "url": "https://www.reddit.com/r/stocks/comments/9eoceb/bayn_good_time_to_buy/", "whitelist_status": "all_ads", "wls": 6}, {"author": "GreenScreen20", "author_flair_css_class": null, "author_flair_richtext": [], "author_flair_text": null, "author_flair_type": "text", "author_fullname": "t2_jbfin", "can_mod_post": false, "contest_mode": false, "created_utc": 1536622054, "domain": "self.stocks", "full_link": "https://www.reddit.com/r/stocks/comments/9es8cl/atvi_will_black_ops_4_battle_royale_be_the_next/", "gilded": 0, "id": "9es8cl", "is_crosspostable": true, "is_meta": false, "is_original_content": false, "is_reddit_media_domain": false, "is_self": true, "is_video": false, "link_flair_background_color": "", "link_flair_richtext": [], "link_flair_text_color": "dark", "link_flair_type": "text", "locked": false, "media_only": false, "no_follow": true, "num_comments": 18, "num_crossposts": 0, "over_18": false, "parent_whitelist_status": "all_ads", "permalink": "/r/stocks/comments/9es8cl/atvi_will_black_ops_4_battle_royale_be_the_next/", "pinned": false, "pwls": 6, "retrieved_on": 1536622055, "score": 1, "selftext": "Really considering putting more money in ATVI, looking at some of the black ops footage it seems they've finally done something new with COD.  \n\n\nDo you guys think this could revitalize the call of duty franchise?  ", "send_replies": true, "spoiler": false, "stickied": false, "subreddit": "stocks", "subreddit_id": "t5_2qjfk", "subreddit_subscribers": 269226, "subreddit_type": "public", "thumbnail": "self", "title": "ATVI - Will Black Ops 4 Battle Royale be the next Fortnite?", "url": "https://www.reddit.com/r/stocks/comments/9es8cl/atvi_will_black_ops_4_battle_royale_be_the_next/", "whitelist_status": "all_ads", "wls": 6}, {"author": "jetsettr", "author_flair_css_class": null, "author_flair_richtext": [], "author_flair_text": null, "author_flair_type": "text", "author_fullname": "t2_vmbel5u", "can_mod_post": false, "contest_mode": false, "created_utc": 1536629567, "domain": "self.stocks", "full_link": "https://www.reddit.com/r/stocks/comments/9et4s4/free_stock_for_signing_up_for_webull_broker/", "gilded": 0, "id": "9et4s4", "is_crosspostable": false, "is_meta": false, "is_original_content": false, "is_reddit_media_domain": false, "is_self": true, "is_video": false, "link_flair_background_color": "", "link_flair_richtext": [], "link_flair_text_color": "dark", "link_flair_type": "text", "locked": false, "media_only": false, "no_follow": true, "num_comments": 0, "num_crossposts": 0, "over_18": false, "parent_whitelist_status": "all_ads", "permalink": "/r/stocks/comments/9et4s4/free_stock_for_signing_up_for_webull_broker/", "pinned": false, "pwls": 6, "retrieved_on": 1536629568, "score": 1, "selftext": "[removed]", "send_replies": true, "spoiler": false, "stickied": false, "subreddit": "stocks", "subreddit_id": "t5_2qjfk", "subreddit_subscribers": 269258, "subreddit_type": "public", "thumbnail": "self", "title": "Free stock for signing up for Webull broker.", "url": "https://www.reddit.com/r/stocks/comments/9et4s4/free_stock_for_signing_up_for_webull_broker/", "whitelist_status": "all_ads", "wls": 6}, {"author": "horsedong", "author_flair_css_class": null, "author_flair_richtext": [], "author_flair_text": null, "author_flair_type": "text", "author_fullname": "t2_gpeo5", "can_mod_post": false, "contest_mode": false, "created_utc": 1536615618, "domain": "self.stocks", "full_link": "https://www.reddit.com/r/stocks/comments/9ere2g/cvna/", "gilded": 0, "id": "9ere2g", "is_crosspostable": true, "is_meta": false, "is_original_content": false, "is_reddit_media_domain": false, "is_self": true, "is_video": false, "link_flair_background_color": "", "link_flair_richtext": [], "link_flair_text_color": "dark", "link_flair_type": "text", "locked": false, "media_only": false, "no_follow": true, "num_comments": 3, "num_crossposts": 0, "over_18": false, "parent_whitelist_status": "all_ads", "permalink": "/r/stocks/comments/9ere2g/cvna/", "pinned": false, "pwls": 6, "retrieved_on": 1536615619, "score": 1, "selftext": "CVNA was up 11% today. What are your thoughts on the stock and if you see continued upside potential? \n\nCVNA seems to have an incredibly scalable model and could ultimately take down the car dealership industry.\n\nMy only concern is with the CEO\u2019s Dad being the largest shareholder and a convicted felon. Is this a warranted concern? ", "send_replies": true, "spoiler": false, "stickied": false, "subreddit": "stocks", "subreddit_id": "t5_2qjfk", "subreddit_subscribers": 269189, "subreddit_type": "public", "thumbnail": "self", "title": "CVNA", "url": "https://www.reddit.com/r/stocks/comments/9ere2g/cvna/", "whitelist_status": "all_ads", "wls": 6}, {"author": "cokeandmacbook", "author_flair_css_class": null, "author_flair_richtext": [], "author_flair_text": null, "author_flair_type": "text", "author_fullname": "t2_15jz93", "can_mod_post": false, "contest_mode": false, "created_utc": 1536620400, "domain": "self.stocks", "full_link": "https://www.reddit.com/r/stocks/comments/9es0op/need_help_from_an_equity_trader_from_an/", "gilded": 0, "id": "9es0op", "is_crosspostable": true, "is_meta": false, "is_original_content": false, "is_reddit_media_domain": false, "is_self": true, "is_video": false, "link_flair_background_color": "", "link_flair_richtext": [], "link_flair_text_color": "dark", "link_flair_type": "text", "locked": false, "media_only": false, "no_follow": true, "num_comments": 2, "num_crossposts": 0, "over_18": false, "parent_whitelist_status": "all_ads", "permalink": "/r/stocks/comments/9es0op/need_help_from_an_equity_trader_from_an/", "pinned": false, "pwls": 6, "retrieved_on": 1536620401, "score": 1, "selftext": "I work for a recruitment firm and want to open equity trading in London. I have a few questions that I would really appreciate if you can help me understand. \n\n1. What are the different equity trading desks and sub desks called and how do they differ from each other? \n2. What area of equity trading is booming / going to be in the future? \n3. What are the book names for equity options traders (e.g. do they trade by region and if so which regions? , is it by sector e.g TMT and what are all the sectors for options books? , is it by index or single stocks and so on? \n4. My background is in FX but Equities is a completely new area for me so trying to understand it well. \n\nThank you very much. ", "send_replies": true, "spoiler": false, "stickied": false, "subreddit": "stocks", "subreddit_id": "t5_2qjfk", "subreddit_subscribers": 269216, "subreddit_type": "public", "thumbnail": "self", "title": "Need help from an Equity Trader from an Investment Bank please?", "url": "https://www.reddit.com/r/stocks/comments/9es0op/need_help_from_an_equity_trader_from_an/", "whitelist_status": "all_ads", "wls": 6}, {"author": "taiwansteez", "author_flair_css_class": null, "author_flair_richtext": [], "author_flair_text": null, "author_flair_type": "text", "author_fullname": "t2_101l4c3i", "can_mod_post": false, "contest_mode": false, "created_utc": 1536627303, "domain": "self.stocks", "full_link": "https://www.reddit.com/r/stocks/comments/9esvb9/should_i_sell_my_cgc_shares_and_put_the_money_in/", "gilded": 0, "id": "9esvb9", "is_crosspostable": true, "is_meta": false, "is_original_content": false, "is_reddit_media_domain": false, "is_self": true, "is_video": false, "link_flair_background_color": "", "link_flair_richtext": [], "link_flair_text_color": "dark", "link_flair_type": "text", "locked": false, "media_only": false, "no_follow": true, "num_comments": 5, "num_crossposts": 0, "over_18": false, "parent_whitelist_status": "all_ads", "permalink": "/r/stocks/comments/9esvb9/should_i_sell_my_cgc_shares_and_put_the_money_in/", "pinned": false, "pwls": 6, "retrieved_on": 1536627304, "score": 1, "selftext": "I only started investing this year and this is my first time experiencing 90%+ gains on a single stock and it has been a wild ride. CGC's valuation is absolutely insane at this point and I'm thinking I should take my profits and re-balance the CGC portion of my portfolio into a cannabis ETF like $MJ to still be exposed(but safer-ish) to the potential future gains of legalization.\n\n&amp;#x200B;\n\nMy only concern is that holding an ETF like MJ is really no different than holding CGC because all the weed stocks move in tandem however taking a basket approach towards the industry seems much safer. Not sure what to do here so I've come to reddit lol. Also I'm a little bitter and baffled that TLRY has out-gained CGC so much but I shouldn't complain", "send_replies": true, "spoiler": false, "stickied": false, "subreddit": "stocks", "subreddit_id": "t5_2qjfk", "subreddit_subscribers": 269252, "subreddit_type": "public", "thumbnail": "self", "title": "Should I sell my CGC shares and put the money in a Marijuana ETF?", "url": "https://www.reddit.com/r/stocks/comments/9esvb9/should_i_sell_my_cgc_shares_and_put_the_money_in/", "whitelist_status": "all_ads", "wls": 6}, {"author": "philmcp", "author_flair_css_class": null, "author_flair_richtext": [], "author_flair_text": null, "author_flair_type": "text", "author_fullname": "t2_y2rt2", "can_mod_post": false, "contest_mode": false, "created_utc": 1536629884, "domain": "self.stocks", "full_link": "https://www.reddit.com/r/stocks/comments/9et62f/7_tweets_which_wiped_40_billion_off_the_stock/", "gilded": 0, "id": "9et62f", "is_crosspostable": false, "is_meta": false, "is_original_content": false, "is_reddit_media_domain": false, "is_self": true, "is_video": false, "link_flair_background_color": "", "link_flair_richtext": [], "link_flair_text_color": "dark", "link_flair_type": "text", "locked": false, "media_only": false, "no_follow": true, "num_comments": 1, "num_crossposts": 0, "over_18": false, "parent_whitelist_status": "all_ads", "permalink": "/r/stocks/comments/9et62f/7_tweets_which_wiped_40_billion_off_the_stock/", "pinned": false, "post_hint": "self", "preview": {"enabled": false, "images": [{"id": "Jw6dBOgltNGjr2n_9OtRPsy7qrvz25TRYzc1mdbh8sM", "resolutions": [{"height": 60, "url": "https://i.redditmedia.com/bRlMMmUl6mOFQnCE7tJJ-2LWbhuSPU311WfG1nru954.jpg?fit=crop&amp;crop=faces%2Centropy&amp;arh=2&amp;w=108&amp;s=79c0b31500144f8150fe7775e7a61773", "width": 108}, {"height": 121, "url": "https://i.redditmedia.com/bRlMMmUl6mOFQnCE7tJJ-2LWbhuSPU311WfG1nru954.jpg?fit=crop&amp;crop=faces%2Centropy&amp;arh=2&amp;w=216&amp;s=3a68adc5ad81b07dd2731484a511dae9", "width": 216}, {"height": 179, "url": "https://i.redditmedia.com/bRlMMmUl6mOFQnCE7tJJ-2LWbhuSPU311WfG1nru954.jpg?fit=crop&amp;crop=faces%2Centropy&amp;arh=2&amp;w=320&amp;s=70af2f055025caa4a8496d893e2c9931", "width": 320}, {"height": 359, "url": "https://i.redditmedia.com/bRlMMmUl6mOFQnCE7tJJ-2LWbhuSPU311WfG1nru954.jpg?fit=crop&amp;crop=faces%2Centropy&amp;arh=2&amp;w=640&amp;s=366bbc5a390d484e3536dc7fa25803b3", "width": 640}], "source": {"height": 421, "url": "https://i.redditmedia.com/bRlMMmUl6mOFQnCE7tJJ-2LWbhuSPU311WfG1nru954.jpg?s=1ad16f6a46f897defbbe878c29e82450", "width": 750}, "variants": {}}]}, "pwls": 6, "retrieved_on": 1536629885, "score": 1, "selftext": "[removed]", "send_replies": true, "spoiler": false, "stickied": false, "subreddit": "stocks", "subreddit_id": "t5_2qjfk", "subreddit_subscribers": 269258, "subreddit_type": "public", "thumbnail": "self", "title": "7 tweets which wiped $40 billion off the stock market", "url": "https://www.reddit.com/r/stocks/comments/9et62f/7_tweets_which_wiped_40_billion_off_the_stock/", "whitelist_status": "all_ads", "wls": 6}, {"author": "padlock_emoji", "author_flair_css_class": null, "author_flair_richtext": [], "author_flair_text": null, "author_flair_type": "text", "author_fullname": "t2_vgja1", "can_mod_post": false, "contest_mode": false, "created_utc": 1536600278, "domain": "self.stocks", "full_link": "https://www.reddit.com/r/stocks/comments/9ep62r/go_tesla/", "gilded": 0, "id": "9ep62r", "is_crosspostable": false, "is_meta": false, "is_original_content": false, "is_reddit_media_domain": false, "is_self": true, "is_video": false, "link_flair_background_color": "", "link_flair_richtext": [], "link_flair_text_color": "dark", "link_flair_type": "text", "locked": false, "media_only": false, "no_follow": true, "num_comments": 1, "num_crossposts": 0, "over_18": false, "parent_whitelist_status": "all_ads", "permalink": "/r/stocks/comments/9ep62r/go_tesla/", "pinned": false, "pwls": 6, "retrieved_on": 1536600282, "score": 1, "selftext": "[removed]", "send_replies": true, "spoiler": false, "stickied": false, "subreddit": "stocks", "subreddit_id": "t5_2qjfk", "subreddit_subscribers": 269106, "subreddit_type": "public", "thumbnail": "self", "title": "Go Tesla!", "url": "https://www.reddit.com/r/stocks/comments/9ep62r/go_tesla/", "whitelist_status": "all_ads", "wls": 6}, {"author": "bmtz5", "author_flair_css_class": null, "author_flair_richtext": [], "author_flair_text": null, "author_flair_type": "text", "author_fullname": "t2_mg8xd", "can_mod_post": false, "contest_mode": false, "created_utc": 1536555914, "domain": "self.stocks", "full_link": "https://www.reddit.com/r/stocks/comments/9ejvu1/where_do_you_go_for_stock_data/", "gilded": 0, "id": "9ejvu1", "is_crosspostable": false, "is_meta": false, "is_original_content": false, "is_reddit_media_domain": false, "is_self": true, "is_video": false, "link_flair_background_color": "", "link_flair_richtext": [], "link_flair_text_color": "dark", "link_flair_type": "text", "locked": false, "media_only": false, "no_follow": true, "num_comments": 0, "num_crossposts": 0, "over_18": false, "parent_whitelist_status": "all_ads", "permalink": "/r/stocks/comments/9ejvu1/where_do_you_go_for_stock_data/", "pinned": false, "pwls": 6, "retrieved_on": 1536555915, "score": 1, "selftext": "[removed]", "send_replies": true, "spoiler": false, "stickied": false, "subreddit": "stocks", "subreddit_id": "t5_2qjfk", "subreddit_subscribers": 268946, "subreddit_type": "public", "thumbnail": "self", "title": "Where do you go for stock data?", "url": "https://www.reddit.com/r/stocks/comments/9ejvu1/where_do_you_go_for_stock_data/", "whitelist_status": "all_ads", "wls": 6}, {"author": "PretendSchedule", "author_flair_css_class": null, "author_flair_richtext": [], "author_flair_text": null, "author_flair_type": "text", "author_fullname": "t2_26n2mll2", "can_mod_post": false, "contest_mode": false, "created_utc": 1536622379, "domain": "self.stocks", "full_link": "https://www.reddit.com/r/stocks/comments/9es9ss/is_there_an_app_that_will_set_an_alarm_at/", "gilded": 0, "id": "9es9ss", "is_crosspostable": false, "is_meta": false, "is_original_content": false, "is_reddit_media_domain": false, "is_self": true, "is_video": false, "link_flair_background_color": "", "link_flair_richtext": [], "link_flair_text_color": "dark", "link_flair_type": "text", "locked": false, "media_only": false, "no_follow": true, "num_comments": 0, "num_crossposts": 0, "over_18": false, "parent_whitelist_status": "all_ads", "permalink": "/r/stocks/comments/9es9ss/is_there_an_app_that_will_set_an_alarm_at/", "pinned": false, "pwls": 6, "retrieved_on": 1536622380, "score": 1, "selftext": "[removed]", "send_replies": true, "spoiler": false, "stickied": false, "subreddit": "stocks", "subreddit_id": "t5_2qjfk", "subreddit_subscribers": 269226, "subreddit_type": "public", "thumbnail": "self", "title": "Is there an app that will set an alarm at different stock prices?", "url": "https://www.reddit.com/r/stocks/comments/9es9ss/is_there_an_app_that_will_set_an_alarm_at/", "whitelist_status": "all_ads", "wls": 6}, {"author": "Pewe1337", "author_flair_css_class": null, "author_flair_richtext": [], "author_flair_text": null, "author_flair_type": "text", "author_fullname": "t2_1447p7", "can_mod_post": false, "contest_mode": false, "created_utc": 1536596565, "domain": "self.stocks", "full_link": "https://www.reddit.com/r/stocks/comments/9eomps/im_so_annoyed_right_now/", "gilded": 0, "id": "9eomps", "is_crosspostable": true, "is_meta": false, "is_original_content": false, "is_reddit_media_domain": false, "is_self": true, "is_video": false, "link_flair_background_color": "", "link_flair_richtext": [], "link_flair_text_color": "dark", "link_flair_type": "text", "locked": false, "media_only": false, "no_follow": true, "num_comments": 7, "num_crossposts": 0, "over_18": false, "parent_whitelist_status": "all_ads", "permalink": "/r/stocks/comments/9eomps/im_so_annoyed_right_now/", "pinned": false, "pwls": 6, "retrieved_on": 1536596567, "score": 0, "selftext": "my local stockbroker went offline for 30 minutes during the starting day, and tsla stocks went up $10 immideatly and I couldnt buy in. Then I decided to wait even more cause I was just so frustrated even though I shouldve bought myself in. Then now the tsla stocks are up $20 each share. Do I buy now or do I keep on waiting? Im so pissed right now.", "send_replies": true, "spoiler": false, "stickied": false, "subreddit": "stocks", "subreddit_id": "t5_2qjfk", "subreddit_subscribers": 269089, "subreddit_type": "public", "thumbnail": "self", "title": "im so annoyed right now", "url": "https://www.reddit.com/r/stocks/comments/9eomps/im_so_annoyed_right_now/", "whitelist_status": "all_ads", "wls": 6}, {"author": "nanananawhatsmyname", "author_flair_css_class": null, "author_flair_richtext": [], "author_flair_text": null, "author_flair_type": "text", "author_fullname": "t2_1ewv9vpb", "can_mod_post": false, "contest_mode": false, "created_utc": 1536599845, "domain": "self.stocks", "full_link": "https://www.reddit.com/r/stocks/comments/9ep3s1/basic_stock_market_questions/", "gilded": 0, "id": "9ep3s1", "is_crosspostable": true, "is_meta": false, "is_original_content": false, "is_reddit_media_domain": false, "is_self": true, "is_video": false, "link_flair_background_color": "", "link_flair_richtext": [], "link_flair_text_color": "dark", "link_flair_type": "text", "locked": false, "media_only": false, "no_follow": true, "num_comments": 4, "num_crossposts": 0, "over_18": false, "parent_whitelist_status": "all_ads", "permalink": "/r/stocks/comments/9ep3s1/basic_stock_market_questions/", "pinned": false, "pwls": 6, "retrieved_on": 1536599846, "score": 0, "selftext": "If I buy 0.001% of the stocks in something like Google or I guess Alphabet, will they wire 0.001% of the revenue to my bank account? What if I buy 5%? What is the point of investing if the answer is no? Sorry for my extreme ignorance on this topic. ", "send_replies": true, "spoiler": false, "stickied": false, "subreddit": "stocks", "subreddit_id": "t5_2qjfk", "subreddit_subscribers": 269108, "subreddit_type": "public", "thumbnail": "self", "title": "Basic stock market questions", "url": "https://www.reddit.com/r/stocks/comments/9ep3s1/basic_stock_market_questions/", "whitelist_status": "all_ads", "wls": 6}, {"author": "fpl_uk", "author_flair_css_class": null, "author_flair_richtext": [], "author_flair_text": null, "author_flair_type": "text", "author_fullname": "t2_1txmxyba", "can_mod_post": false, "contest_mode": false, "created_utc": 1536603974, "domain": "self.stocks", "full_link": "https://www.reddit.com/r/stocks/comments/9eppf5/uk_brokerage_services/", "gilded": 0, "id": "9eppf5", "is_crosspostable": true, "is_meta": false, "is_original_content": false, "is_reddit_media_domain": false, "is_self": true, "is_video": false, "link_flair_background_color": "", "link_flair_richtext": [], "link_flair_text_color": "dark", "link_flair_type": "text", "locked": false, "media_only": false, "no_follow": true, "num_comments": 1, "num_crossposts": 0, "over_18": false, "parent_whitelist_status": "all_ads", "permalink": "/r/stocks/comments/9eppf5/uk_brokerage_services/", "pinned": false, "pwls": 6, "retrieved_on": 1536603975, "score": 0, "selftext": "Just been denied placing Stop Losses on US stocks in my Hargreaves Lansdown account (UK) - does anyone know a brokerage service that would allow me to hold overseas equity and apply stop losses to these please?\n\nThanks ", "send_replies": true, "spoiler": false, "stickied": false, "subreddit": "stocks", "subreddit_id": "t5_2qjfk", "subreddit_subscribers": 269128, "subreddit_type": "public", "thumbnail": "self", "title": "UK Brokerage Services", "url": "https://www.reddit.com/r/stocks/comments/9eppf5/uk_brokerage_services/", "whitelist_status": "all_ads", "wls": 6}, {"author": "mheals77", "author_flair_css_class": null, "author_flair_richtext": [], "author_flair_text": null, "author_flair_type": "text", "author_fullname": "t2_112w6y", "can_mod_post": false, "contest_mode": false, "created_utc": 1536555141, "domain": "self.stocks", "full_link": "https://www.reddit.com/r/stocks/comments/9ejsvz/stock_picks/", "gilded": 0, "id": "9ejsvz", "is_crosspostable": true, "is_meta": false, "is_original_content": false, "is_reddit_media_domain": false, "is_self": true, "is_video": false, "link_flair_background_color": "", "link_flair_richtext": [], "link_flair_text_color": "dark", "link_flair_type": "text", "locked": false, "media_only": false, "no_follow": true, "num_comments": 6, "num_crossposts": 0, "over_18": false, "parent_whitelist_status": "all_ads", "permalink": "/r/stocks/comments/9ejsvz/stock_picks/", "pinned": false, "pwls": 6, "retrieved_on": 1536555141, "score": 0, "selftext": "I am curious if anyone knows any good shows or youtube videos that are updated regularly that highlight good picks that could be happening. I already watch Mad Money daily and would like to add more to that list, but I am looking for something more focused on picking stock.", "send_replies": true, "spoiler": false, "stickied": false, "subreddit": "stocks", "subreddit_id": "t5_2qjfk", "subreddit_subscribers": 268940, "subreddit_type": "public", "thumbnail": "self", "title": "Stock Picks", "url": "https://www.reddit.com/r/stocks/comments/9ejsvz/stock_picks/", "whitelist_status": "all_ads", "wls": 6}, {"author": "randomy917191", "author_flair_css_class": null, "author_flair_richtext": [], "author_flair_text": null, "author_flair_type": "text", "author_fullname": "t2_218wh8r6", "can_mod_post": false, "contest_mode": false, "created_utc": 1536585095, "domain": "self.stocks", "full_link": "https://www.reddit.com/r/stocks/comments/9en0fm/penny_stock_skyrocketing_in_pre_market_this/", "gilded": 0, "id": "9en0fm", "is_crosspostable": true, "is_meta": false, "is_original_content": false, "is_reddit_media_domain": false, "is_self": true, "is_video": false, "link_flair_background_color": "", "link_flair_richtext": [], "link_flair_text_color": "dark", "link_flair_type": "text", "locked": false, "media_only": false, "no_follow": true, "num_comments": 7, "num_crossposts": 0, "over_18": false, "parent_whitelist_status": "all_ads", "permalink": "/r/stocks/comments/9en0fm/penny_stock_skyrocketing_in_pre_market_this/", "pinned": false, "pwls": 6, "retrieved_on": 1536585096, "score": 0, "selftext": "I was holding penny retail stock for awhile while it dipped and woke up this morning to \ud83d\udcaf increase and gaining due to a sudden buyout announcement. The market isn\u2019t even open. How high can I expect it to go? Should I sell today and get my $ back or keep holding? Will the merger make it 400% or more?", "send_replies": true, "spoiler": false, "stickied": false, "subreddit": "stocks", "subreddit_id": "t5_2qjfk", "subreddit_subscribers": 269018, "subreddit_type": "public", "thumbnail": "self", "title": "Penny Stock Skyrocketing in Pre market this morning", "url": "https://www.reddit.com/r/stocks/comments/9en0fm/penny_stock_skyrocketing_in_pre_market_this/", "whitelist_status": "all_ads", "wls": 6}, {"author": "MrComedyKing", "author_flair_css_class": null, "author_flair_richtext": [], "author_flair_text": null, "author_flair_type": "text", "author_fullname": "t2_a438t", "can_mod_post": false, "contest_mode": false, "created_utc": 1536626284, "domain": "self.stocks", "full_link": "https://www.reddit.com/r/stocks/comments/9esqwo/bullish_on_avp_stock_soon_to_rocket/", "gilded": 0, "id": "9esqwo", "is_crosspostable": true, "is_meta": false, "is_original_content": false, "is_reddit_media_domain": false, "is_self": true, "is_video": false, "link_flair_background_color": "", "link_flair_richtext": [], "link_flair_text_color": "dark", "link_flair_type": "text", "locked": false, "media_only": false, "no_follow": true, "num_comments": 2, "num_crossposts": 0, "over_18": false, "parent_whitelist_status": "all_ads", "permalink": "/r/stocks/comments/9esqwo/bullish_on_avp_stock_soon_to_rocket/", "pinned": false, "pwls": 6, "retrieved_on": 1536626285, "score": 0, "selftext": "New management and a focus on customer/employee satisfaction and expansion will soon pay off for the long time cosmetic manufacturer \n\nWasn\u2019t that long ago they were a $30 SP \u2014 at anything under $2.00 I\u2019d say it\u2019s an advisable Buy In entry point \u2014 probably won\u2019t be a $10 company until 2020 but could easily see it hit 5$ by end of 2019 1st quarter ", "send_replies": true, "spoiler": false, "stickied": false, "subreddit": "stocks", "subreddit_id": "t5_2qjfk", "subreddit_subscribers": 269242, "subreddit_type": "public", "thumbnail": "self", "title": "BULLISH on AVP \u2014 Stock soon to rocket", "url": "https://www.reddit.com/r/stocks/comments/9esqwo/bullish_on_avp_stock_soon_to_rocket/", "whitelist_status": "all_ads", "wls": 6}]